{
    "maintainer": null,
    "private": false,
    "maintainer_email": null,
    "revision_timestamp": null,
    "keywords": "",
    "metadata_modified": "2016-10-27 13:41:38.590937",
    "temporal_granularity": "",
    "concepts_eurovoc": [],
    "license_id": null,
    "type": "dataset",
    "resources": [
        {
            "mimetype": null,
            "mimetype_inner": "",
            "hash": "",
            "description": "SPARQL endpoint for querying and creating applications based on the most recent data.",
            "format": "http://publications.europa.eu/resource/authority/file-type/SPARQLQ",
            "url": "http://digital-agenda-data.eu/data/sparql",
            "created": "2016-10-27 15:41:39.804146",
            "tracking_summary": null,
            "name": "SPARQL endpoint of the entire parent dataset.",
            "state": "http://publications.europa.eu/resource/authority/dataset-status/COMPLETED",
            "last_modified": "",
            "download_total_resource": "5",
            "url_type": null,
            "position": null,
            "iframe_code": "",
            "datastore_active": false,
            "id": "http://data.europa.eu/88u/distribution/44d7055f-833e-409a-ae7e-c69ef5ec730f",
            "resource_type": "http://publications.europa.eu/resource/authority/distribution-type/WEB_SERVICE",
            "size": ""
        },
        {
            "mimetype": null,
            "mimetype_inner": "",
            "hash": "",
            "description": "Zipped and N3-formatted entire parent dataset: digital-agenda-scoreboard-key-indicators",
            "format": "http://publications.europa.eu/resource/authority/file-type/RDF_N_TRIPLES",
            "url": "http://digital-agenda-data.eu/download/digital-agenda-scoreboard-key-indicators.ttl.zip",
            "created": "2016-10-27 15:41:39.804163",
            "tracking_summary": null,
            "name": "N3/Turtle download of the entire parent dataset.",
            "state": "http://publications.europa.eu/resource/authority/dataset-status/COMPLETED",
            "last_modified": "",
            "download_total_resource": "5",
            "url_type": null,
            "position": null,
            "iframe_code": "",
            "datastore_active": false,
            "id": "http://data.europa.eu/88u/distribution/1989b4fa-96a1-47b3-a61e-8b41a39500fc",
            "resource_type": "http://publications.europa.eu/resource/authority/distribution-type/DOWNLOADABLE_FILE",
            "size": ""
        },
        {
            "mimetype": null,
            "mimetype_inner": "",
            "hash": "",
            "description": "All indicator observations in CSV format. A simple query that returns table-file having a flat structure, with one row for each statistical observation and one column for each dimension or attribute.",
            "format": "http://publications.europa.eu/resource/authority/file-type/CSV",
            "url": "http://digital-agenda-data.eu/sparql?query=PREFIX+sdmx-measure%3A+%3Chttp%3A%2F%2Fpurl.org%2Flinked-data%2Fsdmx%2F2009%2Fmeasure%23%3E%0APREFIX+dad-prop%3A+%3Chttp%3A%2F%2Fsemantic.digital-agenda-data.eu%2Fdef%2Fproperty%2F%3E%0APREFIX+cube%3A+%3Chttp%3A%2F%2Fpurl.org%2Flinked-data%2Fcube%23%3E%0A%0ASELECT%0A++bif%3Asubseq%28str%28%3Ftime%29%2C+bif%3Astrrchr%28bif%3Areplace%28str%28%3Ftime%29%2C+%27%2F%27%2C+%27%23%27%29%2C+%27%23%27%29+%2B+1%29+as+%3Ftime_period%0A++bif%3Asubseq%28str%28%3FrefArea%29%2C+bif%3Astrrchr%28bif%3Areplace%28str%28%3FrefArea%29%2C+%27%2F%27%2C+%27%23%27%29%2C+%27%23%27%29+%2B+1%29+as+%3Fref_area%0A++bif%3Asubseq%28str%28%3Findic%29%2C+bif%3Astrrchr%28bif%3Areplace%28str%28%3Findic%29%2C+%27%2F%27%2C+%27%23%27%29%2C+%27%23%27%29+%2B+1%29+as+%3Findicator%0A++bif%3Asubseq%28str%28%3Fbrkdwn%29%2C+bif%3Astrrchr%28bif%3Areplace%28str%28%3Fbrkdwn%29%2C+%27%2F%27%2C+%27%23%27%29%2C+%27%23%27%29+%2B+1%29+as+%3Fbreakdown%0A++bif%3Asubseq%28str%28%3Funit%29%2C+bif%3Astrrchr%28bif%3Areplace%28str%28%3Funit%29%2C+%27%2F%27%2C+%27%23%27%29%2C+%27%23%27%29+%2B+1%29+as+%3Funit_measure%0A++str%28%3Fval%29+as+%3Fvalue%0AWHERE+%7B%0A++%3Fs+a+cube%3AObservation+.%0A++%3Fs+dad-prop%3Atime-period+%3Ftime+.%0A++%3Fs+dad-prop%3Aref-area+%3FrefArea+.%0A++%3Fs+dad-prop%3Aindicator+%3Findic+.%0A++%3Fs+dad-prop%3Abreakdown+%3Fbrkdwn+.%0A++%3Fs+dad-prop%3Aunit-measure+%3Funit+.%0A++%3Fs+sdmx-measure%3AobsValue+%3Fval+.%0A++%3Fs+cube%3AdataSet+%3Chttp%3A%2F%2Fsemantic.digital-agenda-data.eu%2Fdataset%2Fdigital-agenda-scoreboard-key-indicators%3E+.%0A++filter+%28%3Findic+%3D+%3Chttp%3A%2F%2Fsemantic.digital-agenda-data.eu%2Fcodelist%2Findicator%2Ftel_ftr%3E%29%0A%7D%0Aorder+by+%3Ftime_period+%3Fref_area+%3Findicator+%3Fbreakdown+%3Funit_measure&format=text%2Fcsv",
            "created": "2016-10-27 15:41:39.804128",
            "tracking_summary": null,
            "name": "All available observations for the indicator, in CSV format.",
            "state": "http://publications.europa.eu/resource/authority/dataset-status/COMPLETED",
            "last_modified": "",
            "download_total_resource": "10",
            "url_type": null,
            "position": null,
            "iframe_code": "",
            "datastore_active": false,
            "id": "http://data.europa.eu/88u/distribution/a1f833ec-350c-4bd0-998e-79769ebe8b49",
            "resource_type": "http://publications.europa.eu/resource/authority/distribution-type/DOWNLOADABLE_FILE",
            "size": ""
        },
        {
            "mimetype": null,
            "mimetype_inner": "",
            "hash": "",
            "description": "All indicator observations in RDF/XML format. A simple query that returns observations as triples in RDF/XML format.",
            "format": "http://publications.europa.eu/resource/authority/file-type/RDF_XML",
            "url": "http://digital-agenda-data.eu/sparql?query=PREFIX+dad-prop%3A+%3Chttp%3A%2F%2Fsemantic.digital-agenda-data.eu%2Fdef%2Fproperty%2F%3E%0APREFIX+cube%3A+%3Chttp%3A%2F%2Fpurl.org%2Flinked-data%2Fcube%23%3E%0A%0ACONSTRUCT+%7B+%3Fs+%3Fp+%3Fo+%7D+WHERE+%7B%0A++%3Fs+%3Fp+%3Fo+.%0A++%3Fs+a+cube%3AObservation+.%0A++%3Fs+dad-prop%3Aindicator+%3Chttp%3A%2F%2Fsemantic.digital-agenda-data.eu%2Fcodelist%2Findicator%2Ftel_ftr%3E+.%0A++%3Fs+cube%3AdataSet+%3Chttp%3A%2F%2Fsemantic.digital-agenda-data.eu%2Fdataset%2Fdigital-agenda-scoreboard-key-indicators%3E%0A%7D&format=application%2Frdf%2Bxml",
            "created": "2016-10-27 15:41:39.804139",
            "tracking_summary": null,
            "name": "All available observations for the indicator, in RDF/XML format.",
            "state": "http://publications.europa.eu/resource/authority/dataset-status/COMPLETED",
            "last_modified": "",
            "download_total_resource": "5",
            "url_type": null,
            "position": null,
            "iframe_code": "",
            "datastore_active": false,
            "id": "http://data.europa.eu/88u/distribution/624e18e9-5beb-4d5c-9b19-2aa458d8a9a5",
            "resource_type": "http://publications.europa.eu/resource/authority/distribution-type/DOWNLOADABLE_FILE",
            "size": ""
        },
        {
            "mimetype": null,
            "mimetype_inner": "",
            "hash": "",
            "description": "Zipped and CSV-formatted entire parent dataset: digital-agenda-scoreboard-key-indicators",
            "format": "http://publications.europa.eu/resource/authority/file-type/CSV",
            "url": "http://digital-agenda-data.eu/download/digital-agenda-scoreboard-key-indicators.csv.zip",
            "created": "2016-10-27 15:41:39.804151",
            "tracking_summary": null,
            "name": "CSV download of the entire parent dataset.",
            "state": "http://publications.europa.eu/resource/authority/dataset-status/COMPLETED",
            "last_modified": "2016-10-26 00:00:00",
            "download_total_resource": "5",
            "url_type": null,
            "position": null,
            "iframe_code": "",
            "datastore_active": false,
            "id": "http://data.europa.eu/88u/distribution/eacaa2cb-3901-479c-89db-f96586824df1",
            "resource_type": "http://publications.europa.eu/resource/authority/distribution-type/DOWNLOADABLE_FILE",
            "size": ""
        },
        {
            "mimetype": null,
            "mimetype_inner": null,
            "hash": "",
            "description": "Dynamically generated visualizations (i.e. charts, diagrams) of the dataset contents.",
            "format": "",
            "url": "http://digital-agenda-data.eu/charts/analyse-one-indicator-and-compare-countries#chart={\"indicator-group\":\"any\",\"indicator\":\"tel_ftr\"}",
            "created": null,
            "tracking_summary": null,
            "name": "Dataset visualizations.",
            "state": null,
            "last_modified": null,
            "download_total_resource": null,
            "url_type": null,
            "position": null,
            "iframe_code": null,
            "datastore_active": false,
            "id": "http://data.europa.eu/88u/document/0df848ea-9299-4199-949d-485f697ab46d",
            "resource_type": "http://publications.europa.eu/resource/authority/documentation-type/DOCUMENTATION_RELATED",
            "size": null
        },
        {
            "mimetype": null,
            "mimetype_inner": null,
            "hash": "",
            "description": "Main information about metadata, structure, links to downloads, used in the parent dataset this indicator comes from.",
            "format": "",
            "url": "http://digital-agenda-data.eu/datasets/digital_agenda_scoreboard_key_indicators",
            "created": null,
            "tracking_summary": null,
            "name": "Parent dataset homepage.",
            "state": null,
            "last_modified": null,
            "download_total_resource": null,
            "url_type": null,
            "position": null,
            "iframe_code": null,
            "datastore_active": false,
            "id": "http://data.europa.eu/88u/document/0d31b319-063e-4aff-b831-36ed98b6854b",
            "resource_type": "http://publications.europa.eu/resource/authority/documentation-type/DOCUMENTATION_MAIN",
            "size": null
        },
        {
            "mimetype": null,
            "mimetype_inner": null,
            "hash": "",
            "description": "RDF/XML formatted Data Structrue Definition of the parent dataset.",
            "format": "",
            "url": "http://digital-agenda-data.eu/datasets/digital_agenda_scoreboard_key_indicators/@@structure",
            "created": null,
            "tracking_summary": null,
            "name": "Data Structrue Definition of the parent dataset.",
            "state": null,
            "last_modified": null,
            "download_total_resource": null,
            "url_type": null,
            "position": null,
            "iframe_code": null,
            "datastore_active": false,
            "id": "http://data.europa.eu/88u/document/bcec45a5-1ee0-45dd-af5e-a4edea7db445",
            "resource_type": "http://publications.europa.eu/resource/authority/documentation-type/DOCUMENTATION_RELATED",
            "size": null
        },
        {
            "mimetype": null,
            "mimetype_inner": null,
            "hash": "",
            "description": "RDF/XML formatted codelists for metadata used in the parent dataset this indicator comes from.",
            "format": "",
            "url": "http://digital-agenda-data.eu/datasets/digital_agenda_scoreboard_key_indicators/@@codelists",
            "created": null,
            "tracking_summary": null,
            "name": "Metadata codelists used in the parent dataset.",
            "state": null,
            "last_modified": null,
            "download_total_resource": null,
            "url_type": null,
            "position": null,
            "iframe_code": null,
            "datastore_active": false,
            "id": "http://data.europa.eu/88u/document/908c0562-6895-4e16-9dbf-eb9ae49691c7",
            "resource_type": "http://publications.europa.eu/resource/authority/documentation-type/DOCUMENTATION_RELATED",
            "size": null
        }
    ],
    "interoperability_level": null,
    "name": "BoKUq6nmo3evY0QaGKWHFQ",
    "isopen": true,
    "accrual_periodicity": "http://data.europa.eu/euodp/kos/accrual-periodicity/other",
    "owner_org": "d7c6596e-9b6e-4461-a6b8-3cfeba1da887",
    "geographical_coverage": [
        "http://publications.europa.eu/resource/authority/country/ROU",
        "http://publications.europa.eu/resource/authority/country/SVK",
        "http://publications.europa.eu/resource/authority/country/SVN",
        "http://publications.europa.eu/resource/authority/country/SWE",
        "http://publications.europa.eu/resource/authority/country/MLT",
        "http://publications.europa.eu/resource/authority/country/NLD",
        "http://publications.europa.eu/resource/authority/country/POL",
        "http://publications.europa.eu/resource/authority/country/PRT",
        "http://publications.europa.eu/resource/authority/country/BEL",
        "http://publications.europa.eu/resource/authority/country/AUT",
        "http://publications.europa.eu/resource/authority/country/CYP",
        "http://publications.europa.eu/resource/authority/country/BGR",
        "http://publications.europa.eu/resource/authority/country/DEU",
        "http://publications.europa.eu/resource/authority/country/CZE",
        "http://publications.europa.eu/resource/authority/country/ESP",
        "http://publications.europa.eu/resource/authority/country/DNK",
        "http://publications.europa.eu/resource/authority/country/FIN",
        "http://publications.europa.eu/resource/authority/country/EST",
        "http://publications.europa.eu/resource/authority/country/GBR",
        "http://publications.europa.eu/resource/authority/country/FRA",
        "http://publications.europa.eu/resource/authority/country/HRV",
        "http://publications.europa.eu/resource/authority/country/GRC",
        "http://publications.europa.eu/resource/authority/country/IRL",
        "http://publications.europa.eu/resource/authority/country/HUN",
        "http://publications.europa.eu/resource/authority/country/LTU",
        "http://publications.europa.eu/resource/authority/country/ITA",
        "http://publications.europa.eu/resource/authority/country/LVA",
        "http://publications.europa.eu/resource/authority/country/LUX"
    ],
    "revision_id": null,
    "identifier": "tel_ftr",
    "version_description": "",
    "extras": [],
    "relationships_as_object": [],
    "tag_string": null,
    "temporal_coverage_to": "",
    "num_tags": null,
    "id": "BoKUq6nmo3evY0QaGKWHFQ",
    "metadata_created": "2016-10-27 13:41:38.373349",
    "modified_date": "2016-10-27 13:41:38.590937",
    "capacity": "public",
    "author": null,
    "author_email": null,
    "type_of_dataset": [
        "http://publications.europa.eu/resource/authority/dataset-type/STATISTICAL"
    ],
    "state": null,
    "version": "",
    "creator_user_id": null,
    "status": "http://data.europa.eu/euodp/kos/dataset-status/Completed",
    "num_resources": 5,
    "description": "Wholesale call termination charges of the incumbent operator in fixed voice tecephony for local calls\n\n### Original source\n\nElectronic communications market indicators collected by Commission services, through National Regulatory Authorities, for the Communications Committee (COCOM) - January and July reports.:\n\nhttp://ec.europa.eu/digital-agenda/about-fast-and-ultra-fast-internet-access\n\n### Parent dataset\n\nThis dataset is part of of another dataset:\n\nhttp://digital-agenda-data.eu/datasets/digital_agenda_scoreboard_key_indicators",
    "title": "Fixed voice termination rate",
    "temporal_coverage_from": "2013-01-01T00:00:00",
    "groups": [],
    "relationships_as_subject": [],
    "language": [
        "http://publications.europa.eu/resource/authority/language/ENG"
    ],
    "alternative_title": "Fixed voice termination rate",
    "url": "http://semantic.digital-agenda-data.eu/codelist/indicator/tel_ftr",
    "release_date": "2016-10-27 13:41:38.373349",
    "license_title": null,
    "rdf": null,
    "license_url": "http://data.europa.eu/euodp/kos/licence/EuropeanCommission",
    "organization": {
        "name": "cnect",
        "title": "Directorate-General for Communications Networks, Content and Technology"
    }
}