{
    "maintainer": null,
    "private": false,
    "maintainer_email": null,
    "revision_timestamp": null,
    "keywords": [
        {
            "display_name": "regions",
            "name": "regions"
        },
        {
            "display_name": "region",
            "name": "region"
        }
    ],
    "metadata_modified": "2019-02-15T08:10:15",
    "temporal_granularity": "",
    "concepts_eurovoc": [
        "http://eurovoc.europa.eu/6140"
    ],
    "license_id": null,
    "type": "dataset",
    "resources": [
        {
            "mimetype": null,
            "mimetype_inner": "",
            "hash": "",
            "description": "Download dataset in SDMX-ML format",
            "format": "http://publications.europa.eu/resource/authority/file-type/ZIP",
            "url": "http://ec.europa.eu/eurostat/estat-navtree-portlet-prod/BulkDownloadListing?file=data/tgs00050.sdmx.zip",
            "created": "",
            "tracking_summary": null,
            "name": "Default_Title",
            "state": "",
            "last_modified": "",
            "download_total_resource": "0",
            "url_type": null,
            "position": null,
            "iframe_code": "",
            "datastore_active": false,
            "id": "http://data.europa.eu/88u/distribution/2a53835b-a8cb-4870-b9e3-bbdc0517b7cc",
            "resource_type": "http://publications.europa.eu/resource/authority/distribution-type/DOWNLOADABLE_FILE",
            "size": ""
        },
        {
            "mimetype": null,
            "mimetype_inner": "",
            "hash": "",
            "description": "",
            "format": "http://publications.europa.eu/resource/authority/file-type/OP_DATPRO",
            "url": "http://ec.europa.eu/eurostat/tgm/graph.do?tab=graph&plugin=1&language=en&pcode=tgs00050",
            "created": "",
            "tracking_summary": null,
            "name": "Graph",
            "state": "",
            "last_modified": "",
            "download_total_resource": "0",
            "url_type": null,
            "position": null,
            "iframe_code": "",
            "datastore_active": false,
            "id": "http://data.europa.eu/88u/distribution/717aa4ed-1bb9-4485-b50b-60c578643af2",
            "resource_type": "http://publications.europa.eu/resource/authority/distribution-type/VISUALIZATION",
            "size": ""
        },
        {
            "mimetype": null,
            "mimetype_inner": "",
            "hash": "",
            "description": "Download dataset in TSV format (unzipped)",
            "format": "http://publications.europa.eu/resource/authority/file-type/TSV",
            "url": "http://ec.europa.eu/eurostat/estat-navtree-portlet-prod/BulkDownloadListing?file=data/tgs00050.tsv.gz&unzip=true",
            "created": "",
            "tracking_summary": null,
            "name": "Default_Title",
            "state": "",
            "last_modified": "",
            "download_total_resource": "0",
            "url_type": null,
            "position": null,
            "iframe_code": "",
            "datastore_active": false,
            "id": "http://data.europa.eu/88u/distribution/3a68d7cd-81c7-4812-8c0f-5ca6f3d6a414",
            "resource_type": "http://publications.europa.eu/resource/authority/distribution-type/DOWNLOADABLE_FILE",
            "size": ""
        },
        {
            "mimetype": null,
            "mimetype_inner": "",
            "hash": "",
            "description": "Download dataset in TSV format",
            "format": "http://publications.europa.eu/resource/authority/file-type/ZIP",
            "url": "http://ec.europa.eu/eurostat/estat-navtree-portlet-prod/BulkDownloadListing?file=data/tgs00050.tsv.gz",
            "created": "",
            "tracking_summary": null,
            "name": "Default_Title",
            "state": "",
            "last_modified": "",
            "download_total_resource": "0",
            "url_type": null,
            "position": null,
            "iframe_code": "",
            "datastore_active": false,
            "id": "http://data.europa.eu/88u/distribution/c58d3426-ed8f-400e-af54-77d5f1c3c98e",
            "resource_type": "http://publications.europa.eu/resource/authority/distribution-type/DOWNLOADABLE_FILE",
            "size": ""
        },
        {
            "mimetype": null,
            "mimetype_inner": "",
            "hash": "",
            "description": "",
            "format": "http://publications.europa.eu/resource/authority/file-type/OP_DATPRO",
            "url": "http://ec.europa.eu/eurostat/tgm/mapToolClosed.do?tab=map&init=1&plugin=1&language=en&pcode=tgs00050",
            "created": "",
            "tracking_summary": null,
            "name": "Map",
            "state": "",
            "last_modified": "",
            "download_total_resource": "0",
            "url_type": null,
            "position": null,
            "iframe_code": "",
            "datastore_active": false,
            "id": "http://data.europa.eu/88u/distribution/131b8aa9-bedd-4069-a232-9e1b31b106c7",
            "resource_type": "http://publications.europa.eu/resource/authority/distribution-type/VISUALIZATION",
            "size": ""
        },
        {
            "mimetype": null,
            "mimetype_inner": "",
            "hash": "",
            "description": "",
            "format": "http://publications.europa.eu/resource/authority/file-type/OP_DATPRO",
            "url": "http://ec.europa.eu/eurostat/tgm/table.do?tab=table&plugin=1&language=en&pcode=tgs00050",
            "created": "",
            "tracking_summary": null,
            "name": "Table",
            "state": "",
            "last_modified": "",
            "download_total_resource": "0",
            "url_type": null,
            "position": null,
            "iframe_code": "",
            "datastore_active": false,
            "id": "http://data.europa.eu/88u/distribution/e95665f7-5fbd-4467-a156-ce682253851e",
            "resource_type": "http://publications.europa.eu/resource/authority/distribution-type/VISUALIZATION",
            "size": ""
        },
        {
            "mimetype": null,
            "mimetype_inner": null,
            "hash": "",
            "description": "",
            "format": "http://publications.europa.eu/resource/authority/file-type/OP_DATPRO",
            "url": "http://ec.europa.eu/eurostat/cache/metadata/en/isoc_i_esms.htm",
            "created": null,
            "tracking_summary": null,
            "name": "ESMS metadata (Euro-SDMX Metadata structure) HTML",
            "state": null,
            "last_modified": null,
            "download_total_resource": null,
            "url_type": null,
            "position": null,
            "iframe_code": null,
            "datastore_active": false,
            "id": "http://data.europa.eu/88u/document/a23009f9-9f67-4595-b632-23af4738566b",
            "resource_type": "http://publications.europa.eu/resource/authority/documentation-type/DOCUMENTATION_MAIN",
            "size": null
        },
        {
            "mimetype": null,
            "mimetype_inner": null,
            "hash": "",
            "description": "",
            "format": "http://publications.europa.eu/resource/authority/file-type/OP_DATPRO",
            "url": "http://ec.europa.eu/eurostat/estat-navtree-portlet-prod/BulkDownloadListing?file=metadata/isoc_i_esms.sdmx.zip",
            "created": null,
            "tracking_summary": null,
            "name": "ESMS metadata (Euro-SDMX Metadata structure) SDMX",
            "state": null,
            "last_modified": null,
            "download_total_resource": null,
            "url_type": null,
            "position": null,
            "iframe_code": null,
            "datastore_active": false,
            "id": "http://data.europa.eu/88u/document/66bf7120-4c26-458d-869f-df8e8e23ac86",
            "resource_type": "http://publications.europa.eu/resource/authority/documentation-type/WEBPAGE_RELATED",
            "size": null
        },
        {
            "mimetype": null,
            "mimetype_inner": null,
            "hash": "",
            "description": "",
            "format": "http://publications.europa.eu/resource/authority/file-type/OP_DATPRO",
            "url": "http://ec.europa.eu/eurostat/web/products-datasets/-/tgs00050",
            "created": null,
            "tracking_summary": null,
            "name": "More information on Eurostat Website",
            "state": null,
            "last_modified": null,
            "download_total_resource": null,
            "url_type": null,
            "position": null,
            "iframe_code": null,
            "datastore_active": false,
            "id": "http://data.europa.eu/88u/document/3dff6862-b66f-45f8-9950-09ed0f815e32",
            "resource_type": "http://publications.europa.eu/resource/authority/documentation-type/WEBPAGE_RELATED",
            "size": null
        }
    ],
    "interoperability_level": null,
    "name": "e6a0UhvNMIRFLO1OEcNQw",
    "isopen": true,
    "accrual_periodicity": "",
    "owner_org": "9c0d04b1-a494-4f70-80b2-54024b6f8b0c",
    "geographical_coverage": [],
    "revision_id": null,
    "identifier": "tgs00050",
    "version_description": "",
    "extras": [],
    "relationships_as_object": [],
    "tag_string": null,
    "temporal_coverage_to": "2018-01-01",
    "num_tags": null,
    "id": "e6a0UhvNMIRFLO1OEcNQw",
    "metadata_created": "2015-10-16 10:16:50.912297",
    "modified_date": "2019-01-31",
    "capacity": "public",
    "author": null,
    "author_email": null,
    "type_of_dataset": [
        "http://publications.europa.eu/resource/authority/dataset-type/STATISTICAL"
    ],
    "state": null,
    "version": "",
    "creator_user_id": null,
    "status": "http://data.europa.eu/euodp/kos/dataset-status/Completed",
    "num_resources": 6,
    "description": "Regular users of the internet are persons who use the internet on average at least once a week, every day or almost every day.",
    "title": "Individuals regularly using the internet by NUTS 2 regions",
    "temporal_coverage_from": "2007-01-01",
    "groups": [
        {
            "title": "http://publications.europa.eu/resource/authority/data-theme/EDUC"
        },
        {
            "title": "http://publications.europa.eu/resource/authority/data-theme/ECON"
        }
    ],
    "relationships_as_subject": [],
    "language": [],
    "alternative_title": "",
    "url": "http://ec.europa.eu/eurostat/web/products-datasets/-/tgs00050",
    "release_date": "",
    "license_title": null,
    "rdf": null,
    "license_url": "http://data.europa.eu/euodp/kos/licence/EuropeanCommission",
    "organization": {
        "name": "estat",
        "title": "Eurostat"
    }
}