{
    "maintainer": null,
    "private": false,
    "maintainer_email": null,
    "revision_timestamp": null,
    "keywords": "",
    "metadata_modified": "2019-02-15T08:27:21",
    "temporal_granularity": "",
    "concepts_eurovoc": [
        "http://eurovoc.europa.eu/1280"
    ],
    "license_id": null,
    "type": "dataset",
    "resources": [
        {
            "mimetype": null,
            "mimetype_inner": "",
            "hash": "",
            "description": "Download dataset in TSV format (unzipped)",
            "format": "http://publications.europa.eu/resource/authority/file-type/TSV",
            "url": "http://ec.europa.eu/eurostat/estat-navtree-portlet-prod/BulkDownloadListing?file=data/tgs00061.tsv.gz&unzip=true",
            "created": "",
            "tracking_summary": null,
            "name": "Default_Title",
            "state": "",
            "last_modified": "",
            "download_total_resource": "0",
            "url_type": null,
            "position": null,
            "iframe_code": "",
            "datastore_active": false,
            "id": "http://data.europa.eu/88u/distribution/da4b62f3-439d-4801-ab87-08b58dc1935f",
            "resource_type": "http://publications.europa.eu/resource/authority/distribution-type/DOWNLOADABLE_FILE",
            "size": ""
        },
        {
            "mimetype": null,
            "mimetype_inner": "",
            "hash": "",
            "description": "",
            "format": "http://publications.europa.eu/resource/authority/file-type/OP_DATPRO",
            "url": "http://ec.europa.eu/eurostat/tgm/table.do?tab=table&plugin=1&language=en&pcode=tgs00061",
            "created": "",
            "tracking_summary": null,
            "name": "Table",
            "state": "",
            "last_modified": "",
            "download_total_resource": "0",
            "url_type": null,
            "position": null,
            "iframe_code": "",
            "datastore_active": false,
            "id": "http://data.europa.eu/88u/distribution/f02bb1f9-7e13-42b0-abab-75e8eb89bc5e",
            "resource_type": "http://publications.europa.eu/resource/authority/distribution-type/VISUALIZATION",
            "size": ""
        },
        {
            "mimetype": null,
            "mimetype_inner": "",
            "hash": "",
            "description": "",
            "format": "http://publications.europa.eu/resource/authority/file-type/OP_DATPRO",
            "url": "http://ec.europa.eu/eurostat/tgm/graph.do?tab=graph&plugin=1&language=en&pcode=tgs00061",
            "created": "",
            "tracking_summary": null,
            "name": "Graph",
            "state": "",
            "last_modified": "",
            "download_total_resource": "0",
            "url_type": null,
            "position": null,
            "iframe_code": "",
            "datastore_active": false,
            "id": "http://data.europa.eu/88u/distribution/2b46b7e2-0485-4d5f-9e58-0482843425a1",
            "resource_type": "http://publications.europa.eu/resource/authority/distribution-type/VISUALIZATION",
            "size": ""
        },
        {
            "mimetype": null,
            "mimetype_inner": "",
            "hash": "",
            "description": "Download dataset in TSV format",
            "format": "http://publications.europa.eu/resource/authority/file-type/ZIP",
            "url": "http://ec.europa.eu/eurostat/estat-navtree-portlet-prod/BulkDownloadListing?file=data/tgs00061.tsv.gz",
            "created": "",
            "tracking_summary": null,
            "name": "Default_Title",
            "state": "",
            "last_modified": "",
            "download_total_resource": "0",
            "url_type": null,
            "position": null,
            "iframe_code": "",
            "datastore_active": false,
            "id": "http://data.europa.eu/88u/distribution/c9a441c0-32bd-45b5-9d19-878aca05ef15",
            "resource_type": "http://publications.europa.eu/resource/authority/distribution-type/DOWNLOADABLE_FILE",
            "size": ""
        },
        {
            "mimetype": null,
            "mimetype_inner": "",
            "hash": "",
            "description": "",
            "format": "http://publications.europa.eu/resource/authority/file-type/OP_DATPRO",
            "url": "http://ec.europa.eu/eurostat/tgm/mapToolClosed.do?tab=map&init=1&plugin=1&language=en&pcode=tgs00061",
            "created": "",
            "tracking_summary": null,
            "name": "Map",
            "state": "",
            "last_modified": "",
            "download_total_resource": "0",
            "url_type": null,
            "position": null,
            "iframe_code": "",
            "datastore_active": false,
            "id": "http://data.europa.eu/88u/distribution/7e208548-b3e5-49a7-bcd8-a5b3fd7bdc4d",
            "resource_type": "http://publications.europa.eu/resource/authority/distribution-type/VISUALIZATION",
            "size": ""
        },
        {
            "mimetype": null,
            "mimetype_inner": "",
            "hash": "",
            "description": "Download dataset in SDMX-ML format",
            "format": "http://publications.europa.eu/resource/authority/file-type/ZIP",
            "url": "http://ec.europa.eu/eurostat/estat-navtree-portlet-prod/BulkDownloadListing?file=data/tgs00061.sdmx.zip",
            "created": "",
            "tracking_summary": null,
            "name": "Default_Title",
            "state": "",
            "last_modified": "",
            "download_total_resource": "0",
            "url_type": null,
            "position": null,
            "iframe_code": "",
            "datastore_active": false,
            "id": "http://data.europa.eu/88u/distribution/711dad14-02fc-417e-b3b0-e1dfd1d24390",
            "resource_type": "http://publications.europa.eu/resource/authority/distribution-type/DOWNLOADABLE_FILE",
            "size": ""
        },
        {
            "mimetype": null,
            "mimetype_inner": null,
            "hash": "",
            "description": "",
            "format": "http://publications.europa.eu/resource/authority/file-type/OP_DATPRO",
            "url": "http://ec.europa.eu/eurostat/web/products-datasets/-/tgs00061",
            "created": null,
            "tracking_summary": null,
            "name": "More information on Eurostat Website",
            "state": null,
            "last_modified": null,
            "download_total_resource": null,
            "url_type": null,
            "position": null,
            "iframe_code": null,
            "datastore_active": false,
            "id": "http://data.europa.eu/88u/document/9493b4ae-fe0f-4da6-a9d1-fc021800ced5",
            "resource_type": "http://publications.europa.eu/resource/authority/documentation-type/WEBPAGE_RELATED",
            "size": null
        },
        {
            "mimetype": null,
            "mimetype_inner": null,
            "hash": "",
            "description": "",
            "format": "http://publications.europa.eu/resource/authority/file-type/OP_DATPRO",
            "url": "http://ec.europa.eu/eurostat/cache/metadata/en/hlth_cdeath_esms.htm",
            "created": null,
            "tracking_summary": null,
            "name": "ESMS metadata (Euro-SDMX Metadata structure) HTML",
            "state": null,
            "last_modified": null,
            "download_total_resource": null,
            "url_type": null,
            "position": null,
            "iframe_code": null,
            "datastore_active": false,
            "id": "http://data.europa.eu/88u/document/a34bba17-4c82-4988-86db-b21e46e045f9",
            "resource_type": "http://publications.europa.eu/resource/authority/documentation-type/DOCUMENTATION_MAIN",
            "size": null
        },
        {
            "mimetype": null,
            "mimetype_inner": null,
            "hash": "",
            "description": "",
            "format": "http://publications.europa.eu/resource/authority/file-type/OP_DATPRO",
            "url": "http://ec.europa.eu/eurostat/estat-navtree-portlet-prod/BulkDownloadListing?file=metadata/hlth_cdeath_esms.sdmx.zip",
            "created": null,
            "tracking_summary": null,
            "name": "ESMS metadata (Euro-SDMX Metadata structure) SDMX",
            "state": null,
            "last_modified": null,
            "download_total_resource": null,
            "url_type": null,
            "position": null,
            "iframe_code": null,
            "datastore_active": false,
            "id": "http://data.europa.eu/88u/document/68ef750d-bf42-45b4-afd8-31b02f2a7f36",
            "resource_type": "http://publications.europa.eu/resource/authority/documentation-type/WEBPAGE_RELATED",
            "size": null
        }
    ],
    "interoperability_level": null,
    "name": "EKOXRYjNhesAQuITmAln3w",
    "isopen": true,
    "accrual_periodicity": "",
    "owner_org": "9c0d04b1-a494-4f70-80b2-54024b6f8b0c",
    "geographical_coverage": [],
    "revision_id": null,
    "identifier": "tgs00061",
    "version_description": "",
    "extras": [],
    "relationships_as_object": [],
    "tag_string": null,
    "temporal_coverage_to": "2010-01-01",
    "num_tags": null,
    "id": "EKOXRYjNhesAQuITmAln3w",
    "metadata_created": "2015-10-16 10:22:09.198968",
    "modified_date": "2018-10-24",
    "capacity": "public",
    "author": null,
    "author_email": null,
    "type_of_dataset": [
        "http://publications.europa.eu/resource/authority/dataset-type/STATISTICAL"
    ],
    "state": null,
    "version": "",
    "creator_user_id": null,
    "status": "http://data.europa.eu/euodp/kos/dataset-status/Completed",
    "num_resources": 6,
    "description": "Causes of Death data refer to the underlying cause which - according to the World Health Organisation (WHO) - is the disease or injury which initiated the train of morbid events leading directly to death, or the circumstances of the accident or violence which produced the fatal injury\". Death due to transport accidents refer to all kind of transport (road: car, pedestrian, cyclist, ..; water; air; ...).",
    "title": "Death due to transport accidents by NUTS 2 regions",
    "temporal_coverage_from": "1999-01-01",
    "groups": [
        {
            "title": "http://publications.europa.eu/resource/authority/data-theme/HEAL"
        },
        {
            "title": "http://publications.europa.eu/resource/authority/data-theme/EDUC"
        },
        {
            "title": "http://publications.europa.eu/resource/authority/data-theme/SOCI"
        }
    ],
    "relationships_as_subject": [],
    "language": [],
    "alternative_title": "",
    "url": "http://ec.europa.eu/eurostat/web/products-datasets/-/tgs00061",
    "release_date": "",
    "license_title": null,
    "rdf": null,
    "license_url": "http://data.europa.eu/euodp/kos/licence/EuropeanCommission",
    "organization": {
        "name": "estat",
        "title": "Eurostat"
    }
}