{
    "maintainer": null,
    "private": false,
    "maintainer_email": null,
    "revision_timestamp": null,
    "keywords": "",
    "metadata_modified": "2019-02-08T08:14:48",
    "temporal_granularity": "",
    "concepts_eurovoc": [],
    "license_id": null,
    "type": "dataset",
    "resources": [
        {
            "mimetype": null,
            "mimetype_inner": "",
            "hash": "",
            "description": "Download dataset in TSV format (unzipped)",
            "format": "http://publications.europa.eu/resource/authority/file-type/TSV",
            "url": "http://ec.europa.eu/eurostat/estat-navtree-portlet-prod/BulkDownloadListing?file=data/sdg_04_60.tsv.gz&unzip=true",
            "created": "",
            "tracking_summary": null,
            "name": "Default_Title",
            "state": "",
            "last_modified": "",
            "download_total_resource": "0",
            "url_type": null,
            "position": null,
            "iframe_code": "",
            "datastore_active": false,
            "id": "http://data.europa.eu/88u/distribution/10fa885c-4990-4dcb-83d3-81e5a1f0f9a7",
            "resource_type": "http://publications.europa.eu/resource/authority/distribution-type/DOWNLOADABLE_FILE",
            "size": ""
        },
        {
            "mimetype": null,
            "mimetype_inner": "",
            "hash": "",
            "description": "Download dataset in TSV format",
            "format": "http://publications.europa.eu/resource/authority/file-type/ZIP",
            "url": "http://ec.europa.eu/eurostat/estat-navtree-portlet-prod/BulkDownloadListing?file=data/sdg_04_60.tsv.gz",
            "created": "",
            "tracking_summary": null,
            "name": "Default_Title",
            "state": "",
            "last_modified": "",
            "download_total_resource": "0",
            "url_type": null,
            "position": null,
            "iframe_code": "",
            "datastore_active": false,
            "id": "http://data.europa.eu/88u/distribution/9ecff0c3-5837-48c8-9489-7f3ee54384bb",
            "resource_type": "http://publications.europa.eu/resource/authority/distribution-type/DOWNLOADABLE_FILE",
            "size": ""
        },
        {
            "mimetype": null,
            "mimetype_inner": "",
            "hash": "",
            "description": "",
            "format": "http://publications.europa.eu/resource/authority/file-type/OP_DATPRO",
            "url": "http://ec.europa.eu/eurostat/tgm/mapToolClosed.do?tab=map&init=1&plugin=1&language=en&pcode=sdg_04_60",
            "created": "",
            "tracking_summary": null,
            "name": "Map",
            "state": "",
            "last_modified": "",
            "download_total_resource": "0",
            "url_type": null,
            "position": null,
            "iframe_code": "",
            "datastore_active": false,
            "id": "http://data.europa.eu/88u/distribution/b6e41f56-bed2-4391-87af-bdd89d82cefa",
            "resource_type": "http://publications.europa.eu/resource/authority/distribution-type/VISUALIZATION",
            "size": ""
        },
        {
            "mimetype": null,
            "mimetype_inner": "",
            "hash": "",
            "description": "",
            "format": "http://publications.europa.eu/resource/authority/file-type/OP_DATPRO",
            "url": "http://ec.europa.eu/eurostat/tgm/table.do?tab=table&plugin=1&language=en&pcode=sdg_04_60",
            "created": "",
            "tracking_summary": null,
            "name": "Table",
            "state": "",
            "last_modified": "",
            "download_total_resource": "0",
            "url_type": null,
            "position": null,
            "iframe_code": "",
            "datastore_active": false,
            "id": "http://data.europa.eu/88u/distribution/92fcc5eb-f45f-4b7b-9f18-09a3a5df58f2",
            "resource_type": "http://publications.europa.eu/resource/authority/distribution-type/VISUALIZATION",
            "size": ""
        },
        {
            "mimetype": null,
            "mimetype_inner": "",
            "hash": "",
            "description": "Download dataset in SDMX-ML format",
            "format": "http://publications.europa.eu/resource/authority/file-type/ZIP",
            "url": "http://ec.europa.eu/eurostat/estat-navtree-portlet-prod/BulkDownloadListing?file=data/sdg_04_60.sdmx.zip",
            "created": "",
            "tracking_summary": null,
            "name": "Default_Title",
            "state": "",
            "last_modified": "",
            "download_total_resource": "0",
            "url_type": null,
            "position": null,
            "iframe_code": "",
            "datastore_active": false,
            "id": "http://data.europa.eu/88u/distribution/cce94b45-f1c7-4df5-b742-d352f59a6163",
            "resource_type": "http://publications.europa.eu/resource/authority/distribution-type/DOWNLOADABLE_FILE",
            "size": ""
        },
        {
            "mimetype": null,
            "mimetype_inner": "",
            "hash": "",
            "description": "",
            "format": "http://publications.europa.eu/resource/authority/file-type/OP_DATPRO",
            "url": "http://ec.europa.eu/eurostat/tgm/graph.do?tab=graph&plugin=1&language=en&pcode=sdg_04_60",
            "created": "",
            "tracking_summary": null,
            "name": "Graph",
            "state": "",
            "last_modified": "",
            "download_total_resource": "0",
            "url_type": null,
            "position": null,
            "iframe_code": "",
            "datastore_active": false,
            "id": "http://data.europa.eu/88u/distribution/d1ee7bb9-e870-4370-9d5a-750679ffdd82",
            "resource_type": "http://publications.europa.eu/resource/authority/distribution-type/VISUALIZATION",
            "size": ""
        },
        {
            "mimetype": null,
            "mimetype_inner": null,
            "hash": "",
            "description": "",
            "format": "http://publications.europa.eu/resource/authority/file-type/OP_DATPRO",
            "url": "http://ec.europa.eu/eurostat/cache/metadata/en/sdg_04_60_esmsip2.htm",
            "created": null,
            "tracking_summary": null,
            "name": "ESMS metadata (Euro-SDMX Metadata structure) HTML",
            "state": null,
            "last_modified": null,
            "download_total_resource": null,
            "url_type": null,
            "position": null,
            "iframe_code": null,
            "datastore_active": false,
            "id": "http://data.europa.eu/88u/document/ce4a2a6f-c02e-408c-8a93-d26297312507",
            "resource_type": "http://publications.europa.eu/resource/authority/documentation-type/DOCUMENTATION_MAIN",
            "size": null
        },
        {
            "mimetype": null,
            "mimetype_inner": null,
            "hash": "",
            "description": "",
            "format": "http://publications.europa.eu/resource/authority/file-type/OP_DATPRO",
            "url": "http://ec.europa.eu/eurostat/web/products-datasets/-/sdg_04_60",
            "created": null,
            "tracking_summary": null,
            "name": "More information on Eurostat Website",
            "state": null,
            "last_modified": null,
            "download_total_resource": null,
            "url_type": null,
            "position": null,
            "iframe_code": null,
            "datastore_active": false,
            "id": "http://data.europa.eu/88u/document/085d3d48-999d-47ba-a403-1f00ce5c4f66",
            "resource_type": "http://publications.europa.eu/resource/authority/documentation-type/WEBPAGE_RELATED",
            "size": null
        },
        {
            "mimetype": null,
            "mimetype_inner": null,
            "hash": "",
            "description": "",
            "format": "http://publications.europa.eu/resource/authority/file-type/OP_DATPRO",
            "url": "http://ec.europa.eu/eurostat/estat-navtree-portlet-prod/BulkDownloadListing?file=metadata/sdg_04_60_esmsip2.sdmx.zip",
            "created": null,
            "tracking_summary": null,
            "name": "ESMS metadata (Euro-SDMX Metadata structure) SDMX",
            "state": null,
            "last_modified": null,
            "download_total_resource": null,
            "url_type": null,
            "position": null,
            "iframe_code": null,
            "datastore_active": false,
            "id": "http://data.europa.eu/88u/document/d54554fe-5377-4390-b1ff-f33a4ba786b0",
            "resource_type": "http://publications.europa.eu/resource/authority/documentation-type/WEBPAGE_RELATED",
            "size": null
        }
    ],
    "interoperability_level": null,
    "name": "N2RkNM4ALZgLvEvlfbGTeA",
    "isopen": true,
    "accrual_periodicity": "",
    "owner_org": "9c0d04b1-a494-4f70-80b2-54024b6f8b0c",
    "geographical_coverage": [],
    "revision_id": null,
    "identifier": "sdg_04_60",
    "version_description": "",
    "extras": [],
    "relationships_as_object": [],
    "tag_string": null,
    "temporal_coverage_to": "2017-01-01",
    "num_tags": null,
    "views_total": "14",
    "id": "N2RkNM4ALZgLvEvlfbGTeA",
    "metadata_created": "2017-11-07 06:35:42.946287",
    "modified_date": "2019-01-15",
    "capacity": "public",
    "author": null,
    "author_email": null,
    "type_of_dataset": [
        "http://publications.europa.eu/resource/authority/dataset-type/STATISTICAL"
    ],
    "state": null,
    "version": "",
    "creator_user_id": null,
    "status": "http://data.europa.eu/euodp/kos/dataset-status/Completed",
    "num_resources": 6,
    "description": "The indicator measures the share of people aged 25 to 64 who stated that they received formal or non-formal education and training in the four weeks preceding the survey (numerator). The denominator consists of the total population of the same age group, excluding those who did not answer to the question 'participation in education and training'. Adult learning covers formal and non-formal learning activities \u2014 both general and vocational \u2014 undertaken by adults after leaving initial education and training. Data stem from the EU Labour Force Survey (EU-LFS).",
    "title": "Adult participation in learning by sex",
    "temporal_coverage_from": "2000-01-01",
    "tracking_summary": "14",
    "groups": [
        {
            "title": "http://publications.europa.eu/resource/authority/data-theme/GOVE"
        }
    ],
    "relationships_as_subject": [],
    "language": [],
    "alternative_title": "",
    "url": "http://ec.europa.eu/eurostat/web/products-datasets/-/sdg_04_60",
    "release_date": "",
    "license_title": null,
    "rdf": null,
    "license_url": "http://data.europa.eu/euodp/kos/licence/EuropeanCommission",
    "organization": {
        "name": "estat",
        "title": "Eurostat"
    }
}