{
    "maintainer": null,
    "private": false,
    "maintainer_email": null,
    "revision_timestamp": null,
    "keywords": [
        {
            "display_name": "europeans",
            "name": "europeans"
        },
        {
            "display_name": "health",
            "name": "health"
        },
        {
            "display_name": "system",
            "name": "system"
        },
        {
            "display_name": "healthcare",
            "name": "healthcare"
        }
    ],
    "metadata_modified": "2019-02-06T15:08:05",
    "temporal_granularity": "",
    "concepts_eurovoc": [],
    "license_id": null,
    "type": "dataset",
    "resources": [
        {
            "mimetype": null,
            "mimetype_inner": "",
            "hash": "",
            "description": "Volume: EB49AA",
            "format": "http://publications.europa.eu/resource/authority/file-type/ZIP",
            "url": "http://ec.europa.eu/COMMFrontOffice/downloadODP/?4926DCC74AD565000440FE2F9AE28FFA",
            "created": "2014-12-02",
            "tracking_summary": null,
            "name": "Link to EB49AA.zip",
            "state": "",
            "last_modified": "",
            "download_total_resource": "0",
            "url_type": null,
            "position": null,
            "iframe_code": "",
            "datastore_active": false,
            "id": "http://data.europa.eu/88u/distribution/33e235fb-9151-4781-8d4f-15f75aea9f9b",
            "resource_type": "http://publications.europa.eu/resource/authority/distribution-type/DOWNLOADABLE_FILE",
            "size": ""
        },
        {
            "mimetype": null,
            "mimetype_inner": "",
            "hash": "",
            "description": "Volume: EB49CFI",
            "format": "http://publications.europa.eu/resource/authority/file-type/ZIP",
            "url": "http://ec.europa.eu/COMMFrontOffice/downloadODP/?38611720D86FA136640B26CE07D58B1A",
            "created": "2014-12-02",
            "tracking_summary": null,
            "name": "Link to EB49CFI.zip",
            "state": "",
            "last_modified": "",
            "download_total_resource": "0",
            "url_type": null,
            "position": null,
            "iframe_code": "",
            "datastore_active": false,
            "id": "http://data.europa.eu/88u/distribution/5f7e009d-be13-4dec-b6f2-130909d87650",
            "resource_type": "http://publications.europa.eu/resource/authority/distribution-type/DOWNLOADABLE_FILE",
            "size": ""
        },
        {
            "mimetype": null,
            "mimetype_inner": "",
            "hash": "",
            "description": "Volume: EB49B",
            "format": "http://publications.europa.eu/resource/authority/file-type/ZIP",
            "url": "http://ec.europa.eu/COMMFrontOffice/downloadODP/?94274F7E9F7B0DD98ECEA6AF0E2951A5",
            "created": "2014-12-02",
            "tracking_summary": null,
            "name": "Link to EB49B.zip",
            "state": "",
            "last_modified": "",
            "download_total_resource": "0",
            "url_type": null,
            "position": null,
            "iframe_code": "",
            "datastore_active": false,
            "id": "http://data.europa.eu/88u/distribution/30b1422c-964e-401c-9b93-cee31ba271a5",
            "resource_type": "http://publications.europa.eu/resource/authority/distribution-type/DOWNLOADABLE_FILE",
            "size": ""
        },
        {
            "mimetype": null,
            "mimetype_inner": "",
            "hash": "",
            "description": "Volume: EB49CPO",
            "format": "http://publications.europa.eu/resource/authority/file-type/ZIP",
            "url": "http://ec.europa.eu/COMMFrontOffice/downloadODP/?8F6458472356DBAF2A54C774C617EF8D",
            "created": "2014-12-02",
            "tracking_summary": null,
            "name": "Link to EB49CPO.zip",
            "state": "",
            "last_modified": "",
            "download_total_resource": "0",
            "url_type": null,
            "position": null,
            "iframe_code": "",
            "datastore_active": false,
            "id": "http://data.europa.eu/88u/distribution/47568036-e06a-4c06-a98d-4c1f2ae07843",
            "resource_type": "http://publications.europa.eu/resource/authority/distribution-type/DOWNLOADABLE_FILE",
            "size": ""
        },
        {
            "mimetype": null,
            "mimetype_inner": "",
            "hash": "",
            "description": "Volume: EB49A",
            "format": "http://publications.europa.eu/resource/authority/file-type/ZIP",
            "url": "http://ec.europa.eu/COMMFrontOffice/downloadODP/?20DCBDC580559B46A66858492D82D7D9",
            "created": "2014-12-02",
            "tracking_summary": null,
            "name": "Link to EB49A.zip",
            "state": "",
            "last_modified": "",
            "download_total_resource": "0",
            "url_type": null,
            "position": null,
            "iframe_code": "",
            "datastore_active": false,
            "id": "http://data.europa.eu/88u/distribution/8150a6ef-7272-436f-ba47-06bdf04044df",
            "resource_type": "http://publications.europa.eu/resource/authority/distribution-type/DOWNLOADABLE_FILE",
            "size": ""
        },
        {
            "mimetype": null,
            "mimetype_inner": "",
            "hash": "",
            "description": "Volume: EB49CDK",
            "format": "http://publications.europa.eu/resource/authority/file-type/ZIP",
            "url": "http://ec.europa.eu/COMMFrontOffice/downloadODP/?BD8B503298C0AF6FD45B0A7F254D9C72",
            "created": "2014-12-02",
            "tracking_summary": null,
            "name": "Link to EB49CDK.zip",
            "state": "",
            "last_modified": "",
            "download_total_resource": "0",
            "url_type": null,
            "position": null,
            "iframe_code": "",
            "datastore_active": false,
            "id": "http://data.europa.eu/88u/distribution/cde6c881-a6b1-4b2e-8e20-d3921e7e53d6",
            "resource_type": "http://publications.europa.eu/resource/authority/distribution-type/DOWNLOADABLE_FILE",
            "size": ""
        },
        {
            "mimetype": null,
            "mimetype_inner": "",
            "hash": "",
            "description": "Volume: EB49CGR",
            "format": "http://publications.europa.eu/resource/authority/file-type/ZIP",
            "url": "http://ec.europa.eu/COMMFrontOffice/downloadODP/?22632102ACB729B5F0EB4CB69C0AB902",
            "created": "2014-12-02",
            "tracking_summary": null,
            "name": "Link to EB49CGR.zip",
            "state": "",
            "last_modified": "",
            "download_total_resource": "0",
            "url_type": null,
            "position": null,
            "iframe_code": "",
            "datastore_active": false,
            "id": "http://data.europa.eu/88u/distribution/e5e061bc-aca4-4bcb-830b-323cc4339a3f",
            "resource_type": "http://publications.europa.eu/resource/authority/distribution-type/DOWNLOADABLE_FILE",
            "size": ""
        },
        {
            "mimetype": null,
            "mimetype_inner": "",
            "hash": "",
            "description": "Volume: EB49CIR",
            "format": "http://publications.europa.eu/resource/authority/file-type/ZIP",
            "url": "http://ec.europa.eu/COMMFrontOffice/downloadODP/?5D15A16453E82BC15E99C478A7001AD6",
            "created": "2014-12-02",
            "tracking_summary": null,
            "name": "Link to EB49CIR.zip",
            "state": "",
            "last_modified": "",
            "download_total_resource": "0",
            "url_type": null,
            "position": null,
            "iframe_code": "",
            "datastore_active": false,
            "id": "http://data.europa.eu/88u/distribution/7cb37b6c-7e3c-409a-8ff7-993207655e5c",
            "resource_type": "http://publications.europa.eu/resource/authority/distribution-type/DOWNLOADABLE_FILE",
            "size": ""
        },
        {
            "mimetype": null,
            "mimetype_inner": "",
            "hash": "",
            "description": "Volume: EB49CUK",
            "format": "http://publications.europa.eu/resource/authority/file-type/ZIP",
            "url": "http://ec.europa.eu/COMMFrontOffice/downloadODP/?4476D81213BFFAA5509F59A23DE04CD0",
            "created": "2014-12-02",
            "tracking_summary": null,
            "name": "Link to EB49CUK.zip",
            "state": "",
            "last_modified": "",
            "download_total_resource": "0",
            "url_type": null,
            "position": null,
            "iframe_code": "",
            "datastore_active": false,
            "id": "http://data.europa.eu/88u/distribution/0b478fca-0e15-42e4-b894-88dc6e1bc405",
            "resource_type": "http://publications.europa.eu/resource/authority/distribution-type/DOWNLOADABLE_FILE",
            "size": ""
        },
        {
            "mimetype": null,
            "mimetype_inner": "",
            "hash": "",
            "description": "Volume: EB49CFR",
            "format": "http://publications.europa.eu/resource/authority/file-type/ZIP",
            "url": "http://ec.europa.eu/COMMFrontOffice/downloadODP/?3168F006D3E7756D6063165A4221C70E",
            "created": "2014-12-02",
            "tracking_summary": null,
            "name": "Link to EB49CFR.zip",
            "state": "",
            "last_modified": "",
            "download_total_resource": "0",
            "url_type": null,
            "position": null,
            "iframe_code": "",
            "datastore_active": false,
            "id": "http://data.europa.eu/88u/distribution/a0ad5634-f6b2-4fa4-8fd1-480c19d41001",
            "resource_type": "http://publications.europa.eu/resource/authority/distribution-type/DOWNLOADABLE_FILE",
            "size": ""
        },
        {
            "mimetype": null,
            "mimetype_inner": "",
            "hash": "",
            "description": "Volume: EB49D",
            "format": "http://publications.europa.eu/resource/authority/file-type/ZIP",
            "url": "http://ec.europa.eu/COMMFrontOffice/downloadODP/?F22181F181F89CAE51E0F31499E62FC3",
            "created": "2014-12-02",
            "tracking_summary": null,
            "name": "Link to EB49D.zip",
            "state": "",
            "last_modified": "",
            "download_total_resource": "0",
            "url_type": null,
            "position": null,
            "iframe_code": "",
            "datastore_active": false,
            "id": "http://data.europa.eu/88u/distribution/4a8da2b1-2fab-45b0-a49b-06dc3f32b06c",
            "resource_type": "http://publications.europa.eu/resource/authority/distribution-type/DOWNLOADABLE_FILE",
            "size": ""
        },
        {
            "mimetype": null,
            "mimetype_inner": "",
            "hash": "",
            "description": "Volume: EB49CNL",
            "format": "http://publications.europa.eu/resource/authority/file-type/ZIP",
            "url": "http://ec.europa.eu/COMMFrontOffice/downloadODP/?E2B996A64EB5811CA7795B5E9537821E",
            "created": "2014-12-02",
            "tracking_summary": null,
            "name": "Link to EB49CNL.zip",
            "state": "",
            "last_modified": "",
            "download_total_resource": "0",
            "url_type": null,
            "position": null,
            "iframe_code": "",
            "datastore_active": false,
            "id": "http://data.europa.eu/88u/distribution/5e5bfe04-941d-4292-ae68-0cf1fb4bb3bf",
            "resource_type": "http://publications.europa.eu/resource/authority/distribution-type/DOWNLOADABLE_FILE",
            "size": ""
        },
        {
            "mimetype": null,
            "mimetype_inner": "",
            "hash": "",
            "description": "Volume: EB49CEG",
            "format": "http://publications.europa.eu/resource/authority/file-type/ZIP",
            "url": "http://ec.europa.eu/COMMFrontOffice/downloadODP/?9FBB256530BE13C41BE0C5802CB4A661",
            "created": "2014-12-02",
            "tracking_summary": null,
            "name": "Link to EB49CEG.zip",
            "state": "",
            "last_modified": "",
            "download_total_resource": "0",
            "url_type": null,
            "position": null,
            "iframe_code": "",
            "datastore_active": false,
            "id": "http://data.europa.eu/88u/distribution/e6904454-87f4-41dd-b2fc-ce2bda82f553",
            "resource_type": "http://publications.europa.eu/resource/authority/distribution-type/DOWNLOADABLE_FILE",
            "size": ""
        },
        {
            "mimetype": null,
            "mimetype_inner": "",
            "hash": "",
            "description": "Volume: EB49CAU",
            "format": "http://publications.europa.eu/resource/authority/file-type/ZIP",
            "url": "http://ec.europa.eu/COMMFrontOffice/downloadODP/?00BCA22DEF685A9E6EF1653AFCF1BF78",
            "created": "2014-12-02",
            "tracking_summary": null,
            "name": "Link to EB49CAU.zip",
            "state": "",
            "last_modified": "",
            "download_total_resource": "0",
            "url_type": null,
            "position": null,
            "iframe_code": "",
            "datastore_active": false,
            "id": "http://data.europa.eu/88u/distribution/c2001c34-bfd8-4868-97ca-183c0cede7a0",
            "resource_type": "http://publications.europa.eu/resource/authority/distribution-type/DOWNLOADABLE_FILE",
            "size": ""
        },
        {
            "mimetype": null,
            "mimetype_inner": "",
            "hash": "",
            "description": "Volume: EB49CLU",
            "format": "http://publications.europa.eu/resource/authority/file-type/ZIP",
            "url": "http://ec.europa.eu/COMMFrontOffice/downloadODP/?15BFA2C1399BBF84FBDC415B208F4B3E",
            "created": "2014-12-02",
            "tracking_summary": null,
            "name": "Link to EB49CLU.zip",
            "state": "",
            "last_modified": "",
            "download_total_resource": "0",
            "url_type": null,
            "position": null,
            "iframe_code": "",
            "datastore_active": false,
            "id": "http://data.europa.eu/88u/distribution/e7b80bbb-1f2e-4191-a74a-68d1646e9715",
            "resource_type": "http://publications.europa.eu/resource/authority/distribution-type/DOWNLOADABLE_FILE",
            "size": ""
        },
        {
            "mimetype": null,
            "mimetype_inner": "",
            "hash": "",
            "description": "Volume: EB49CIT",
            "format": "http://publications.europa.eu/resource/authority/file-type/ZIP",
            "url": "http://ec.europa.eu/COMMFrontOffice/downloadODP/?51EB4786A3305ABDE500C2261318E34A",
            "created": "2014-12-02",
            "tracking_summary": null,
            "name": "Link to EB49CIT.zip",
            "state": "",
            "last_modified": "",
            "download_total_resource": "0",
            "url_type": null,
            "position": null,
            "iframe_code": "",
            "datastore_active": false,
            "id": "http://data.europa.eu/88u/distribution/292c2378-4a77-4f73-a824-3139ba8db258",
            "resource_type": "http://publications.europa.eu/resource/authority/distribution-type/DOWNLOADABLE_FILE",
            "size": ""
        },
        {
            "mimetype": null,
            "mimetype_inner": "",
            "hash": "",
            "description": "Volume: EB49CSW",
            "format": "http://publications.europa.eu/resource/authority/file-type/ZIP",
            "url": "http://ec.europa.eu/COMMFrontOffice/downloadODP/?621EF2C9A740D51D879E8AF2EA2D20DD",
            "created": "2014-12-02",
            "tracking_summary": null,
            "name": "Link to EB49CSW.zip",
            "state": "",
            "last_modified": "",
            "download_total_resource": "0",
            "url_type": null,
            "position": null,
            "iframe_code": "",
            "datastore_active": false,
            "id": "http://data.europa.eu/88u/distribution/203b385f-ae7c-410e-812a-47970656843b",
            "resource_type": "http://publications.europa.eu/resource/authority/distribution-type/DOWNLOADABLE_FILE",
            "size": ""
        },
        {
            "mimetype": null,
            "mimetype_inner": "",
            "hash": "",
            "description": "Volume: EB49CWG",
            "format": "http://publications.europa.eu/resource/authority/file-type/ZIP",
            "url": "http://ec.europa.eu/COMMFrontOffice/downloadODP/?23CBF72EB0908379A29BB68B1480F2B8",
            "created": "2014-12-02",
            "tracking_summary": null,
            "name": "Link to EB49CWG.zip",
            "state": "",
            "last_modified": "",
            "download_total_resource": "0",
            "url_type": null,
            "position": null,
            "iframe_code": "",
            "datastore_active": false,
            "id": "http://data.europa.eu/88u/distribution/4887d10f-78da-427e-9b46-12332f369128",
            "resource_type": "http://publications.europa.eu/resource/authority/distribution-type/DOWNLOADABLE_FILE",
            "size": ""
        },
        {
            "mimetype": null,
            "mimetype_inner": "",
            "hash": "",
            "description": "Volume: EB49CBE",
            "format": "http://publications.europa.eu/resource/authority/file-type/ZIP",
            "url": "http://ec.europa.eu/COMMFrontOffice/downloadODP/?CE61CFC858E4523833056F7969AE41CA",
            "created": "2014-12-02",
            "tracking_summary": null,
            "name": "Link to EB49CBE.zip",
            "state": "",
            "last_modified": "",
            "download_total_resource": "0",
            "url_type": null,
            "position": null,
            "iframe_code": "",
            "datastore_active": false,
            "id": "http://data.europa.eu/88u/distribution/0b05ab43-80b0-427e-adfb-e6facb03549a",
            "resource_type": "http://publications.europa.eu/resource/authority/distribution-type/DOWNLOADABLE_FILE",
            "size": ""
        },
        {
            "mimetype": null,
            "mimetype_inner": "",
            "hash": "",
            "description": "Volume: EB49AP",
            "format": "http://publications.europa.eu/resource/authority/file-type/ZIP",
            "url": "http://ec.europa.eu/COMMFrontOffice/downloadODP/?3E23DC93130C2BD2B85DAAED1E734C10",
            "created": "2014-12-02",
            "tracking_summary": null,
            "name": "Link to EB49AP.zip",
            "state": "",
            "last_modified": "",
            "download_total_resource": "0",
            "url_type": null,
            "position": null,
            "iframe_code": "",
            "datastore_active": false,
            "id": "http://data.europa.eu/88u/distribution/c428f63c-b29b-415d-abc9-1393e1e6ccd1",
            "resource_type": "http://publications.europa.eu/resource/authority/distribution-type/DOWNLOADABLE_FILE",
            "size": ""
        },
        {
            "mimetype": null,
            "mimetype_inner": "",
            "hash": "",
            "description": "Volume: EB49CGE",
            "format": "http://publications.europa.eu/resource/authority/file-type/ZIP",
            "url": "http://ec.europa.eu/COMMFrontOffice/downloadODP/?94396B6F27823B6C238EDD9C16F8F143",
            "created": "2014-12-02",
            "tracking_summary": null,
            "name": "Link to EB49CGE.zip",
            "state": "",
            "last_modified": "",
            "download_total_resource": "0",
            "url_type": null,
            "position": null,
            "iframe_code": "",
            "datastore_active": false,
            "id": "http://data.europa.eu/88u/distribution/c57b370d-9e62-48e4-9409-cb54386b24cc",
            "resource_type": "http://publications.europa.eu/resource/authority/distribution-type/DOWNLOADABLE_FILE",
            "size": ""
        },
        {
            "mimetype": null,
            "mimetype_inner": "",
            "hash": "",
            "description": "Volume: EB49CSP",
            "format": "http://publications.europa.eu/resource/authority/file-type/ZIP",
            "url": "http://ec.europa.eu/COMMFrontOffice/downloadODP/?AC78602033247786DB7A5255E96DD92A",
            "created": "2014-12-02",
            "tracking_summary": null,
            "name": "Link to EB49CSP.zip",
            "state": "",
            "last_modified": "",
            "download_total_resource": "0",
            "url_type": null,
            "position": null,
            "iframe_code": "",
            "datastore_active": false,
            "id": "http://data.europa.eu/88u/distribution/4af3fb41-d75b-48b1-8a9e-3c374bf93f58",
            "resource_type": "http://publications.europa.eu/resource/authority/distribution-type/DOWNLOADABLE_FILE",
            "size": ""
        },
        {
            "mimetype": null,
            "mimetype_inner": null,
            "hash": "",
            "description": "",
            "format": "http://publications.europa.eu/resource/authority/file-type/OP_DATPRO",
            "url": "http://ec.europa.eu/COMMFrontOffice/PublicOpinion/index.cfm/Survey/getSurveyDetail/instruments/SPECIAL/surveyKy/176",
            "created": null,
            "tracking_summary": null,
            "name": "Detailed information on public opinion website",
            "state": null,
            "last_modified": null,
            "download_total_resource": null,
            "url_type": null,
            "position": null,
            "iframe_code": null,
            "datastore_active": false,
            "id": "http://data.europa.eu/88u/document/8077fdba-6c6f-4c5a-8534-5aad0c839fc9",
            "resource_type": "http://publications.europa.eu/resource/authority/documentation-type/DOCUMENTATION_MAIN",
            "size": null
        }
    ],
    "interoperability_level": null,
    "name": "S176_49_0__EBS121",
    "isopen": true,
    "accrual_periodicity": "",
    "owner_org": "dbda9968-cb1e-47c3-b115-245a057e4d4a",
    "geographical_coverage": [
        "http://publications.europa.eu/resource/authority/country/LUX",
        "http://publications.europa.eu/resource/authority/country/ITA",
        "http://publications.europa.eu/resource/authority/country/PRT",
        "http://publications.europa.eu/resource/authority/country/NLD",
        "http://publications.europa.eu/resource/authority/country/SWE",
        "http://publications.europa.eu/resource/authority/country/BEL",
        "http://publications.europa.eu/resource/authority/country/AUT",
        "http://publications.europa.eu/resource/authority/country/DNK",
        "http://publications.europa.eu/resource/authority/country/DEU",
        "http://publications.europa.eu/resource/authority/country/FIN",
        "http://publications.europa.eu/resource/authority/country/ESP",
        "http://publications.europa.eu/resource/authority/country/GBR",
        "http://publications.europa.eu/resource/authority/country/FRA",
        "http://publications.europa.eu/resource/authority/country/IRL",
        "http://publications.europa.eu/resource/authority/country/GRC"
    ],
    "revision_id": null,
    "identifier": "S176_49_0__EBS121",
    "version_description": "",
    "extras": [],
    "relationships_as_object": [],
    "tag_string": null,
    "temporal_coverage_to": "",
    "num_tags": null,
    "id": "S176_49_0__EBS121",
    "metadata_created": "2015-01-15 12:57:47.105655",
    "modified_date": "",
    "capacity": "public",
    "author": null,
    "author_email": null,
    "type_of_dataset": [],
    "state": null,
    "version": "v1.00",
    "creator_user_id": null,
    "status": "http://data.europa.eu/euodp/kos/dataset-status/Completed",
    "num_resources": 22,
    "description": "Le sondage d\u2019opinion analys\u00e9 dans le pr\u00e9sent rapport a \u00e9t\u00e9 effectu\u00e9 dans le cadre de l\u2019EUROBAROMETRE 49, \u00e0 la demande de la Direction G\u00e9n\u00e9rale XXIV, Politique de Consommateurs, de la Commission europ\u00e9enne, entre le 7 avril et le 27 mai 1998, simultan\u00e9ment dans les quinze pays membres de l\u2019Union europ\u00e9enne. Il se fonde sur un ensemble de questions \u00ab nouvelles \u00bb, c'est-\u00e0-dire qui n'ont jamais \u00e9t\u00e9 pos\u00e9es lors d\u2019\u00e9tudes pr\u00e9c\u00e9dentes.\n#####The results by volumes are distributed as follows:\n* Volume A: Countries\n* Volume AA: Groups of countries\n* Volume A' (AP): Trends\n* Volume AA' (AAP): Trends of groups of countries\n* Volume B: EU/socio-demographics\n* Volume B' (BP) : Trends of EU/ socio-demographics \n* Volume C: Country/socio-demographics\n  ----\nResearchers may also contact GESIS - Leibniz Institute for the Social Sciences: [https://www.gesis.org/eurobarometer](https://www.gesis.org/eurobarometer)",
    "title": "Special Eurobarometer 121: Europeans, health, and the healthcare system",
    "temporal_coverage_from": "",
    "groups": [
        {
            "title": "http://publications.europa.eu/resource/authority/data-theme/GOVE"
        }
    ],
    "relationships_as_subject": [],
    "language": [
        "http://publications.europa.eu/resource/authority/language/ENG"
    ],
    "alternative_title": "Europeans, health, and the healthcare system",
    "url": "http://ec.europa.eu/public_opinion/archives/eb_special_140_120_en.htm#121",
    "release_date": "2014-12-10",
    "license_title": null,
    "rdf": null,
    "license_url": "http://data.europa.eu/euodp/kos/licence/EuropeanCommission",
    "organization": {
        "name": "commu",
        "title": "Directorate-General for Communication"
    }
}