{
    "maintainer": null,
    "private": false,
    "maintainer_email": null,
    "revision_timestamp": null,
    "keywords": [
        {
            "display_name": "environment",
            "name": "environment"
        },
        {
            "display_name": "MSFD",
            "name": "MSFD"
        },
        {
            "display_name": "seabed",
            "name": "seabed"
        },
        {
            "display_name": "habitats",
            "name": "habitats"
        }
    ],
    "metadata_modified": "2018-08-29 07:47:54.225968",
    "temporal_granularity": "",
    "concepts_eurovoc": [
        "http://eurovoc.europa.eu/1221",
        "http://eurovoc.europa.eu/1050",
        "http://eurovoc.europa.eu/3149",
        "http://eurovoc.europa.eu/2107",
        "http://eurovoc.europa.eu/6404",
        "http://eurovoc.europa.eu/5742",
        "http://eurovoc.europa.eu/833"
    ],
    "license_id": null,
    "type": "dataset",
    "resources": [
        {
            "mimetype": null,
            "mimetype_inner": "",
            "hash": "",
            "description": "Data product download service of the EMODnet Seabed Habitats portal",
            "format": "http://publications.europa.eu/resource/authority/file-type/ZIP",
            "url": "http://www.emodnet-seabedhabitats.eu/access-data/download-data/",
            "created": "2018-08-14 15:12:59.137568",
            "tracking_summary": null,
            "name": "Download (ESRI shapefile)",
            "state": "http://publications.europa.eu/resource/authority/dataset-status/COMPLETED",
            "last_modified": "",
            "download_total_resource": "27",
            "url_type": null,
            "position": null,
            "iframe_code": "",
            "datastore_active": false,
            "id": "http://data.europa.eu/88u/distribution/22b2109d-af8e-4a3f-9803-719d10c385ea",
            "resource_type": "http://publications.europa.eu/resource/authority/distribution-type/DOWNLOADABLE_FILE",
            "size": ""
        },
        {
            "mimetype": null,
            "mimetype_inner": "",
            "hash": "",
            "description": "WMS Service of the EMODnet Seabed Habitats portal.",
            "format": "http://publications.europa.eu/resource/authority/file-type/PNG",
            "url": "http://52.49.27.224/geoserver/ows/?layers=emodnet:eusm2016&bbox=-4048436.0,2828106.75,4688741.5,1.2556134E7&service=WMS&format=image/png&interpolation=nearest&srs=EPSG:3857&request=GetMap&height=960&width=1600",
            "created": "2018-08-23 11:57:00.950053",
            "tracking_summary": null,
            "name": "Web Map Service (WMS)",
            "state": "http://publications.europa.eu/resource/authority/dataset-status/COMPLETED",
            "last_modified": "",
            "download_total_resource": "2",
            "url_type": null,
            "position": null,
            "iframe_code": "",
            "datastore_active": false,
            "id": "http://data.europa.eu/88u/distribution/0ee8bd1c-d680-40dd-825c-ee6a78e7bdc3",
            "resource_type": "http://publications.europa.eu/resource/authority/distribution-type/VISUALIZATION",
            "size": ""
        },
        {
            "mimetype": null,
            "mimetype_inner": "",
            "hash": "",
            "description": "Web Feature Service (WFS) of the EMODnet Seabed Habitats portal. Maximum number of features per request might be limited.",
            "format": "http://publications.europa.eu/resource/authority/file-type/JSON",
            "url": "http://52.49.27.224/geoserver/ows?SERVICE=WFS&VERSION=1.0.0&request=GetFeature&typeName=emodnet:eusm2016&OUTPUTFORMAT=application/json",
            "created": "2018-08-14 15:12:59.137592",
            "tracking_summary": null,
            "name": "Web Feature Service (WFS)",
            "state": "http://publications.europa.eu/resource/authority/dataset-status/COMPLETED",
            "last_modified": "",
            "download_total_resource": "28",
            "url_type": null,
            "position": null,
            "iframe_code": "",
            "datastore_active": false,
            "id": "http://data.europa.eu/88u/distribution/b1449f5f-b109-46d0-b37f-76cad037d74a",
            "resource_type": "http://publications.europa.eu/resource/authority/distribution-type/WEB_SERVICE",
            "size": ""
        },
        {
            "mimetype": null,
            "mimetype_inner": "",
            "hash": "",
            "description": "Map viewer of the EMODnet Seabed Habitats portal",
            "format": "http://publications.europa.eu/resource/authority/file-type/HTML",
            "url": "http://www.emodnet-seabedhabitats.eu/access-data/launch-map-viewer/",
            "created": "2018-08-14 15:12:59.137587",
            "tracking_summary": null,
            "name": "EMODnet Seabed habitats map viewer",
            "state": "http://publications.europa.eu/resource/authority/dataset-status/COMPLETED",
            "last_modified": "",
            "download_total_resource": "2",
            "url_type": null,
            "position": null,
            "iframe_code": "",
            "datastore_active": false,
            "id": "http://data.europa.eu/88u/distribution/a6416cef-b496-4971-a898-0151443d8f9f",
            "resource_type": "http://publications.europa.eu/resource/authority/distribution-type/VISUALIZATION",
            "size": ""
        },
        {
            "mimetype": null,
            "mimetype_inner": null,
            "hash": "",
            "description": "Metadata record of the dataset",
            "format": "http://publications.europa.eu/resource/authority/file-type/HTML",
            "url": "http://gis.ices.dk/geonetwork/srv/eng/catalog.search#/metadata/02a444c8-bd2d-4e15-8e69-806059103760",
            "created": null,
            "tracking_summary": null,
            "name": "Metadata record",
            "state": null,
            "last_modified": null,
            "download_total_resource": null,
            "url_type": null,
            "position": null,
            "iframe_code": null,
            "datastore_active": false,
            "id": "http://data.europa.eu/88u/document/788956d4-da68-41f2-8936-8dca928121a7",
            "resource_type": "http://publications.europa.eu/resource/authority/documentation-type/DOCUMENTATION_MAIN",
            "size": null
        },
        {
            "mimetype": null,
            "mimetype_inner": null,
            "hash": "",
            "description": "The EMODnet Seabed Habitats website provides a permanent single portal for accessing seabed habitat data in Europe. This includes the EMODnet broad-scale seabed habitat map for Europe (AKA EUSeaMap) and habitat maps from surveys across Europe.",
            "format": "http://publications.europa.eu/resource/authority/file-type/HTML",
            "url": "http://www.emodnet-seabedhabitats.eu/",
            "created": null,
            "tracking_summary": null,
            "name": "EMODnet Seabed Habitats data portal",
            "state": null,
            "last_modified": null,
            "download_total_resource": null,
            "url_type": null,
            "position": null,
            "iframe_code": null,
            "datastore_active": false,
            "id": "http://data.europa.eu/88u/document/419f9b3b-cec6-42de-baa5-d0318aaf1e06",
            "resource_type": "http://publications.europa.eu/resource/authority/documentation-type/WEBPAGE_RELATED",
            "size": null
        }
    ],
    "interoperability_level": null,
    "name": "EMODnet_seabed_habitats_euseamap2",
    "isopen": true,
    "accrual_periodicity": "",
    "owner_org": "344ce8ed-98f3-4c74-aaa8-d2ccf3239841",
    "geographical_coverage": [
        "http://publications.europa.eu/resource/authority/country/ROU",
        "http://publications.europa.eu/resource/authority/country/SVK",
        "http://publications.europa.eu/resource/authority/country/SVN",
        "http://publications.europa.eu/resource/authority/country/SWE",
        "http://publications.europa.eu/resource/authority/country/MLT",
        "http://publications.europa.eu/resource/authority/country/NLD",
        "http://publications.europa.eu/resource/authority/country/POL",
        "http://publications.europa.eu/resource/authority/country/PRT",
        "http://publications.europa.eu/resource/authority/country/BEL",
        "http://publications.europa.eu/resource/authority/country/AUT",
        "http://publications.europa.eu/resource/authority/country/CYP",
        "http://publications.europa.eu/resource/authority/country/BGR",
        "http://publications.europa.eu/resource/authority/country/DEU",
        "http://publications.europa.eu/resource/authority/country/CZE",
        "http://publications.europa.eu/resource/authority/country/ESP",
        "http://publications.europa.eu/resource/authority/country/DNK",
        "http://publications.europa.eu/resource/authority/country/FIN",
        "http://publications.europa.eu/resource/authority/country/EST",
        "http://publications.europa.eu/resource/authority/country/GBR",
        "http://publications.europa.eu/resource/authority/country/FRA",
        "http://publications.europa.eu/resource/authority/country/HRV",
        "http://publications.europa.eu/resource/authority/country/GRC",
        "http://publications.europa.eu/resource/authority/country/IRL",
        "http://publications.europa.eu/resource/authority/country/HUN",
        "http://publications.europa.eu/resource/authority/country/LTU",
        "http://publications.europa.eu/resource/authority/country/ITA",
        "http://publications.europa.eu/resource/authority/country/LVA",
        "http://publications.europa.eu/resource/authority/country/LUX"
    ],
    "revision_id": null,
    "identifier": "02a444c8-bd2d-4e15-8e69-806059103760",
    "version_description": "",
    "extras": [],
    "relationships_as_object": [],
    "tag_string": null,
    "temporal_coverage_to": "",
    "num_tags": null,
    "views_total": "7",
    "id": "EMODnet_seabed_habitats_euseamap2",
    "metadata_created": "2018-08-14 13:12:58.602207",
    "modified_date": "2018-08-29 07:47:54.225968",
    "capacity": "public",
    "author": null,
    "author_email": null,
    "type_of_dataset": [
        "http://publications.europa.eu/resource/authority/dataset-type/MAPPING"
    ],
    "state": null,
    "version": "",
    "creator_user_id": null,
    "status": "http://data.europa.eu/euodp/kos/dataset-status/Completed",
    "num_resources": 4,
    "description": "Output of the 2016 EUSeaMap broad-scale predictive model, produced by EMODnet Seabed Habitats.\r\n\r\nThe extent of the mapped area includes the Mediterranean Sea, Black Sea, Baltic Sea, and areas of the North Eastern Atlantic extending from the Canary Islands in the south to Norway in the North.\r\n\r\nThe map was produced using a \"top-down\" modelling approach using classified habitat descriptors to determine a final output habitat.\r\n\r\nHabitat descriptors differ per region but include:\r\nBiological zone\r\nEnergy class\r\nOxygen regime\r\nSalinity regime\r\nSeabed Substrate\r\nRiverine input\r\n\r\nHabitat descriptors (excepting Substrate) are calculated using underlying physical data and thresholds derived from statistical analyses or expert judgement on known conditions.\r\n\r\nThe model is produced in Arc Model Builder (10.1). \r\n\r\nThe model was created using raster input layers with a cell size of 0.002dd (roughly 250 meters). The model includes the sublittoral zone only; due to the high variability of the littoral zone, a lack of detailed substrate data and the resolution of the model, it is difficult to predict littoral habitats at this scale.\r\n\r\nThe map follows the EUNIS 2007-11 classification system where it is appropriate.\r\nFor details on methodology see:\r\nPopulus J. And Vasquez M. (Eds), 2017. EUSeaMap, a European broad-scale seabed habitat map. Ifremer\r\nAvailable from: http://archimer.ifremer.fr/doc/00388/49975/",
    "title": "EMODnet broad-scale predictive habitat map",
    "temporal_coverage_from": "",
    "tracking_summary": "7",
    "groups": [],
    "relationships_as_subject": [],
    "language": [],
    "alternative_title": "Output of the 2016 EUSeaMap broad-scale predictive model, produced by EMODnet Seabed Habitats.",
    "url": "http://gis.ices.dk/geonetwork/srv/eng/xml.metadata.get?uuid=02a444c8-bd2d-4e15-8e69-806059103760",
    "release_date": "2018-08-14 13:12:58.602207",
    "license_title": null,
    "rdf": null,
    "license_url": "http://data.europa.eu/euodp/kos/licence/EuropeanCommission",
    "organization": {
        "name": "mare",
        "title": "Directorate-General for Maritime Affairs and Fisheries"
    }
}