{
    "maintainer": null,
    "private": false,
    "maintainer_email": null,
    "revision_timestamp": null,
    "keywords": [
        {
            "display_name": "standard",
            "name": "standard"
        },
        {
            "display_name": "opinion",
            "name": "opinion"
        },
        {
            "display_name": "surveys",
            "name": "surveys"
        },
        {
            "display_name": "57",
            "name": "57"
        },
        {
            "display_name": "polls",
            "name": "polls"
        },
        {
            "display_name": "eurobarometer",
            "name": "eurobarometer"
        }
    ],
    "metadata_modified": "2019-02-06T15:09:22",
    "temporal_granularity": "",
    "concepts_eurovoc": [],
    "license_id": null,
    "type": "dataset",
    "resources": [
        {
            "mimetype": null,
            "mimetype_inner": "",
            "hash": "",
            "description": "Volume: EB571-VOLC-DENMARK",
            "format": "http://publications.europa.eu/resource/authority/file-type/ZIP",
            "url": "http://ec.europa.eu/COMMFrontOffice/downloadODP/?700FE080396D0053DECF62D791155FB8",
            "created": "2014-12-02",
            "tracking_summary": null,
            "name": "Link to EB571-VOLC-DENMARK.zip",
            "state": "",
            "last_modified": "",
            "download_total_resource": "0",
            "url_type": null,
            "position": null,
            "iframe_code": "",
            "datastore_active": false,
            "id": "http://data.europa.eu/88u/distribution/49f55bb5-dea3-40ee-b957-880b53347f6f",
            "resource_type": "http://publications.europa.eu/resource/authority/distribution-type/DOWNLOADABLE_FILE",
            "size": ""
        },
        {
            "mimetype": null,
            "mimetype_inner": "",
            "hash": "",
            "description": "Volume: EB571-VOLC-GERMANY",
            "format": "http://publications.europa.eu/resource/authority/file-type/ZIP",
            "url": "http://ec.europa.eu/COMMFrontOffice/downloadODP/?73CA49AC953FD3C4C83B4354A73187FF",
            "created": "2014-12-02",
            "tracking_summary": null,
            "name": "Link to EB571-VOLC-GERMANY.zip",
            "state": "",
            "last_modified": "",
            "download_total_resource": "0",
            "url_type": null,
            "position": null,
            "iframe_code": "",
            "datastore_active": false,
            "id": "http://data.europa.eu/88u/distribution/56ba50ad-f00b-4f58-b270-72a82548028b",
            "resource_type": "http://publications.europa.eu/resource/authority/distribution-type/DOWNLOADABLE_FILE",
            "size": ""
        },
        {
            "mimetype": null,
            "mimetype_inner": "",
            "hash": "",
            "description": "Volume: EB571-VOLC-FINLAND",
            "format": "http://publications.europa.eu/resource/authority/file-type/ZIP",
            "url": "http://ec.europa.eu/COMMFrontOffice/downloadODP/?AF51BB6CD16890CE8BF3035B33063092",
            "created": "2014-12-02",
            "tracking_summary": null,
            "name": "Link to EB571-VOLC-FINLAND.zip",
            "state": "",
            "last_modified": "",
            "download_total_resource": "0",
            "url_type": null,
            "position": null,
            "iframe_code": "",
            "datastore_active": false,
            "id": "http://data.europa.eu/88u/distribution/a1074806-2ea2-4f05-a4b2-ae40ac83f280",
            "resource_type": "http://publications.europa.eu/resource/authority/distribution-type/DOWNLOADABLE_FILE",
            "size": ""
        },
        {
            "mimetype": null,
            "mimetype_inner": "",
            "hash": "",
            "description": "Volume: EB571-VOLC-AUSTRIA",
            "format": "http://publications.europa.eu/resource/authority/file-type/ZIP",
            "url": "http://ec.europa.eu/COMMFrontOffice/downloadODP/?9B2D0720269DBC53FE6CD5AA4917FD81",
            "created": "2014-12-02",
            "tracking_summary": null,
            "name": "Link to EB571-VOLC-AUSTRIA.zip",
            "state": "",
            "last_modified": "",
            "download_total_resource": "0",
            "url_type": null,
            "position": null,
            "iframe_code": "",
            "datastore_active": false,
            "id": "http://data.europa.eu/88u/distribution/d609dc0e-d848-47f1-a00b-40944f426d06",
            "resource_type": "http://publications.europa.eu/resource/authority/distribution-type/DOWNLOADABLE_FILE",
            "size": ""
        },
        {
            "mimetype": null,
            "mimetype_inner": "",
            "hash": "",
            "description": "Volume: EB571VOLA",
            "format": "http://publications.europa.eu/resource/authority/file-type/ZIP",
            "url": "http://ec.europa.eu/COMMFrontOffice/downloadODP/?DEA72CF6FF9B4E442C0643D9A6EDE64D",
            "created": "2014-12-02",
            "tracking_summary": null,
            "name": "Link to EB571VOLA.zip",
            "state": "",
            "last_modified": "",
            "download_total_resource": "0",
            "url_type": null,
            "position": null,
            "iframe_code": "",
            "datastore_active": false,
            "id": "http://data.europa.eu/88u/distribution/ef7d74fa-f2d2-46a7-a0be-46f615cfeda9",
            "resource_type": "http://publications.europa.eu/resource/authority/distribution-type/DOWNLOADABLE_FILE",
            "size": ""
        },
        {
            "mimetype": null,
            "mimetype_inner": "",
            "hash": "",
            "description": "Volume: EB571-VOLC-NORTHERN IRELAND",
            "format": "http://publications.europa.eu/resource/authority/file-type/ZIP",
            "url": "http://ec.europa.eu/COMMFrontOffice/downloadODP/?22357F101F8E3A8AC02625AF5888AE72",
            "created": "2014-12-02",
            "tracking_summary": null,
            "name": "Link to EB571-VOLC-NORTHERN IRELAND.zip",
            "state": "",
            "last_modified": "",
            "download_total_resource": "0",
            "url_type": null,
            "position": null,
            "iframe_code": "",
            "datastore_active": false,
            "id": "http://data.europa.eu/88u/distribution/ef537172-54fe-461c-b1c9-2eda1c1287fe",
            "resource_type": "http://publications.europa.eu/resource/authority/distribution-type/DOWNLOADABLE_FILE",
            "size": ""
        },
        {
            "mimetype": null,
            "mimetype_inner": "",
            "hash": "",
            "description": "Volume: EB571-VOLC-ITALY",
            "format": "http://publications.europa.eu/resource/authority/file-type/ZIP",
            "url": "http://ec.europa.eu/COMMFrontOffice/downloadODP/?AFB06F55BCBBB65C199D567620C4F169",
            "created": "2014-12-02",
            "tracking_summary": null,
            "name": "Link to EB571-VOLC-ITALY.zip",
            "state": "",
            "last_modified": "",
            "download_total_resource": "0",
            "url_type": null,
            "position": null,
            "iframe_code": "",
            "datastore_active": false,
            "id": "http://data.europa.eu/88u/distribution/f25ce6ed-aa2e-4e72-8975-6945dae11991",
            "resource_type": "http://publications.europa.eu/resource/authority/distribution-type/DOWNLOADABLE_FILE",
            "size": ""
        },
        {
            "mimetype": null,
            "mimetype_inner": "",
            "hash": "",
            "description": "Volume: EB571-VOLC-SPAIN",
            "format": "http://publications.europa.eu/resource/authority/file-type/ZIP",
            "url": "http://ec.europa.eu/COMMFrontOffice/downloadODP/?104F62EF4290A6768F374FD23B10E4B0",
            "created": "2014-12-02",
            "tracking_summary": null,
            "name": "Link to EB571-VOLC-SPAIN.zip",
            "state": "",
            "last_modified": "",
            "download_total_resource": "0",
            "url_type": null,
            "position": null,
            "iframe_code": "",
            "datastore_active": false,
            "id": "http://data.europa.eu/88u/distribution/0f7c0faf-0bc4-45cd-a4af-36b1ca77ece4",
            "resource_type": "http://publications.europa.eu/resource/authority/distribution-type/DOWNLOADABLE_FILE",
            "size": ""
        },
        {
            "mimetype": null,
            "mimetype_inner": "",
            "hash": "",
            "description": "Volume: EB571-VOLC-SWEDEN",
            "format": "http://publications.europa.eu/resource/authority/file-type/ZIP",
            "url": "http://ec.europa.eu/COMMFrontOffice/downloadODP/?F8678199D600E18FB153470FBD973826",
            "created": "2014-12-02",
            "tracking_summary": null,
            "name": "Link to EB571-VOLC-SWEDEN.zip",
            "state": "",
            "last_modified": "",
            "download_total_resource": "0",
            "url_type": null,
            "position": null,
            "iframe_code": "",
            "datastore_active": false,
            "id": "http://data.europa.eu/88u/distribution/0a455acf-1e09-42aa-a827-230b0dc3df51",
            "resource_type": "http://publications.europa.eu/resource/authority/distribution-type/DOWNLOADABLE_FILE",
            "size": ""
        },
        {
            "mimetype": null,
            "mimetype_inner": "",
            "hash": "",
            "description": "Volume: EB571-VOLC-BELGIUM",
            "format": "http://publications.europa.eu/resource/authority/file-type/ZIP",
            "url": "http://ec.europa.eu/COMMFrontOffice/downloadODP/?11C299426C85FD6D19DD62BF4655536A",
            "created": "2014-12-02",
            "tracking_summary": null,
            "name": "Link to EB571-VOLC-BELGIUM.zip",
            "state": "",
            "last_modified": "",
            "download_total_resource": "0",
            "url_type": null,
            "position": null,
            "iframe_code": "",
            "datastore_active": false,
            "id": "http://data.europa.eu/88u/distribution/208f5855-607a-4a9f-9472-8210734fa299",
            "resource_type": "http://publications.europa.eu/resource/authority/distribution-type/DOWNLOADABLE_FILE",
            "size": ""
        },
        {
            "mimetype": null,
            "mimetype_inner": "",
            "hash": "",
            "description": "Volume: EB571-VOLC-GREAT BRITAIN",
            "format": "http://publications.europa.eu/resource/authority/file-type/ZIP",
            "url": "http://ec.europa.eu/COMMFrontOffice/downloadODP/?D52F9400FEF6D9B3A50646241A2BBC7A",
            "created": "2014-12-02",
            "tracking_summary": null,
            "name": "Link to EB571-VOLC-GREAT BRITAIN.zip",
            "state": "",
            "last_modified": "",
            "download_total_resource": "0",
            "url_type": null,
            "position": null,
            "iframe_code": "",
            "datastore_active": false,
            "id": "http://data.europa.eu/88u/distribution/a2c8a0ea-467b-4d5f-b699-bb6854e73ee2",
            "resource_type": "http://publications.europa.eu/resource/authority/distribution-type/DOWNLOADABLE_FILE",
            "size": ""
        },
        {
            "mimetype": null,
            "mimetype_inner": "",
            "hash": "",
            "description": "Volume: EB571-VOLC-LUXEMBOURG",
            "format": "http://publications.europa.eu/resource/authority/file-type/ZIP",
            "url": "http://ec.europa.eu/COMMFrontOffice/downloadODP/?99AFD788DB641AD42476F2E3F956024D",
            "created": "2014-12-02",
            "tracking_summary": null,
            "name": "Link to EB571-VOLC-LUXEMBOURG.zip",
            "state": "",
            "last_modified": "",
            "download_total_resource": "0",
            "url_type": null,
            "position": null,
            "iframe_code": "",
            "datastore_active": false,
            "id": "http://data.europa.eu/88u/distribution/ff347324-cb3c-43f6-9bbf-06b2fe284a57",
            "resource_type": "http://publications.europa.eu/resource/authority/distribution-type/DOWNLOADABLE_FILE",
            "size": ""
        },
        {
            "mimetype": null,
            "mimetype_inner": "",
            "hash": "",
            "description": "Volume: EB571-VOLC-NETHERLANDS",
            "format": "http://publications.europa.eu/resource/authority/file-type/ZIP",
            "url": "http://ec.europa.eu/COMMFrontOffice/downloadODP/?E68DC81B9D582620C4FD6E19538D6CC5",
            "created": "2014-12-02",
            "tracking_summary": null,
            "name": "Link to EB571-VOLC-NETHERLANDS.zip",
            "state": "",
            "last_modified": "",
            "download_total_resource": "0",
            "url_type": null,
            "position": null,
            "iframe_code": "",
            "datastore_active": false,
            "id": "http://data.europa.eu/88u/distribution/e4d7e5bd-4dfd-4266-8175-dfb931320de2",
            "resource_type": "http://publications.europa.eu/resource/authority/distribution-type/DOWNLOADABLE_FILE",
            "size": ""
        },
        {
            "mimetype": null,
            "mimetype_inner": "",
            "hash": "",
            "description": "Volume: EB571-VOLC-UK",
            "format": "http://publications.europa.eu/resource/authority/file-type/ZIP",
            "url": "http://ec.europa.eu/COMMFrontOffice/downloadODP/?71174FE282AA18010E459D4BA162728E",
            "created": "2014-12-02",
            "tracking_summary": null,
            "name": "Link to EB571-VOLC-UK.zip",
            "state": "",
            "last_modified": "",
            "download_total_resource": "0",
            "url_type": null,
            "position": null,
            "iframe_code": "",
            "datastore_active": false,
            "id": "http://data.europa.eu/88u/distribution/66e6d4b0-5c08-435b-8d1d-f08c7cff327f",
            "resource_type": "http://publications.europa.eu/resource/authority/distribution-type/DOWNLOADABLE_FILE",
            "size": ""
        },
        {
            "mimetype": null,
            "mimetype_inner": "",
            "hash": "",
            "description": "Volume: EB571-VOLC-PORTUGAL",
            "format": "http://publications.europa.eu/resource/authority/file-type/ZIP",
            "url": "http://ec.europa.eu/COMMFrontOffice/downloadODP/?893D23463D9841E0871CEAB6D5DEC393",
            "created": "2014-12-02",
            "tracking_summary": null,
            "name": "Link to EB571-VOLC-PORTUGAL.zip",
            "state": "",
            "last_modified": "",
            "download_total_resource": "0",
            "url_type": null,
            "position": null,
            "iframe_code": "",
            "datastore_active": false,
            "id": "http://data.europa.eu/88u/distribution/7f4ca606-587f-4980-b5d2-b4978066acb6",
            "resource_type": "http://publications.europa.eu/resource/authority/distribution-type/DOWNLOADABLE_FILE",
            "size": ""
        },
        {
            "mimetype": null,
            "mimetype_inner": "",
            "hash": "",
            "description": "Volume: EB571-VOLC-FRANCE",
            "format": "http://publications.europa.eu/resource/authority/file-type/ZIP",
            "url": "http://ec.europa.eu/COMMFrontOffice/downloadODP/?6189415181F243333D354D09E87B903A",
            "created": "2014-12-02",
            "tracking_summary": null,
            "name": "Link to EB571-VOLC-FRANCE.zip",
            "state": "",
            "last_modified": "",
            "download_total_resource": "0",
            "url_type": null,
            "position": null,
            "iframe_code": "",
            "datastore_active": false,
            "id": "http://data.europa.eu/88u/distribution/e9c65042-3ecf-4f02-aad4-1d69af5173ca",
            "resource_type": "http://publications.europa.eu/resource/authority/distribution-type/DOWNLOADABLE_FILE",
            "size": ""
        },
        {
            "mimetype": null,
            "mimetype_inner": "",
            "hash": "",
            "description": "Volume: EB571-VOLC-IRELAND",
            "format": "http://publications.europa.eu/resource/authority/file-type/ZIP",
            "url": "http://ec.europa.eu/COMMFrontOffice/downloadODP/?411727F7CDD1FE162891C118FD581B59",
            "created": "2014-12-02",
            "tracking_summary": null,
            "name": "Link to EB571-VOLC-IRELAND.zip",
            "state": "",
            "last_modified": "",
            "download_total_resource": "0",
            "url_type": null,
            "position": null,
            "iframe_code": "",
            "datastore_active": false,
            "id": "http://data.europa.eu/88u/distribution/ee8eca65-2a4f-4351-bd30-e47339e26695",
            "resource_type": "http://publications.europa.eu/resource/authority/distribution-type/DOWNLOADABLE_FILE",
            "size": ""
        },
        {
            "mimetype": null,
            "mimetype_inner": "",
            "hash": "",
            "description": "Volume: EB571-VOLC-GREECE",
            "format": "http://publications.europa.eu/resource/authority/file-type/ZIP",
            "url": "http://ec.europa.eu/COMMFrontOffice/downloadODP/?9AFDBB1B5F3EC7D7881E67E12E749A03",
            "created": "2014-12-02",
            "tracking_summary": null,
            "name": "Link to EB571-VOLC-GREECE.zip",
            "state": "",
            "last_modified": "",
            "download_total_resource": "0",
            "url_type": null,
            "position": null,
            "iframe_code": "",
            "datastore_active": false,
            "id": "http://data.europa.eu/88u/distribution/8da975e4-4308-468d-a9a6-d705be459c6e",
            "resource_type": "http://publications.europa.eu/resource/authority/distribution-type/DOWNLOADABLE_FILE",
            "size": ""
        },
        {
            "mimetype": null,
            "mimetype_inner": null,
            "hash": "",
            "description": "",
            "format": "http://publications.europa.eu/resource/authority/file-type/OP_DATPRO",
            "url": "http://ec.europa.eu/COMMFrontOffice/PublicOpinion/index.cfm/Survey/getSurveyDetail/instruments/STANDARD/surveyKy/1401",
            "created": null,
            "tracking_summary": null,
            "name": "Detailed information on public opinion website",
            "state": null,
            "last_modified": null,
            "download_total_resource": null,
            "url_type": null,
            "position": null,
            "iframe_code": null,
            "datastore_active": false,
            "id": "http://data.europa.eu/88u/document/4761bbad-a174-4d76-9e06-7cac9ee62651",
            "resource_type": "http://publications.europa.eu/resource/authority/documentation-type/DOCUMENTATION_MAIN",
            "size": null
        }
    ],
    "interoperability_level": null,
    "name": "S1401_57_1_ST57",
    "isopen": true,
    "accrual_periodicity": "",
    "owner_org": "dbda9968-cb1e-47c3-b115-245a057e4d4a",
    "geographical_coverage": [
        "http://publications.europa.eu/resource/authority/country/LUX",
        "http://publications.europa.eu/resource/authority/country/ITA",
        "http://publications.europa.eu/resource/authority/country/PRT",
        "http://publications.europa.eu/resource/authority/country/NLD",
        "http://publications.europa.eu/resource/authority/country/SWE",
        "http://publications.europa.eu/resource/authority/country/BEL",
        "http://publications.europa.eu/resource/authority/country/AUT",
        "http://publications.europa.eu/resource/authority/country/DNK",
        "http://publications.europa.eu/resource/authority/country/DEU",
        "http://publications.europa.eu/resource/authority/country/FIN",
        "http://publications.europa.eu/resource/authority/country/ESP",
        "http://publications.europa.eu/resource/authority/country/GBR",
        "http://publications.europa.eu/resource/authority/country/FRA",
        "http://publications.europa.eu/resource/authority/country/IRL",
        "http://publications.europa.eu/resource/authority/country/GRC"
    ],
    "revision_id": null,
    "identifier": "S1401_57_1_ST57",
    "version_description": "",
    "extras": [],
    "relationships_as_object": [],
    "tag_string": null,
    "temporal_coverage_to": "",
    "num_tags": null,
    "views_total": "560",
    "id": "S1401_57_1_ST57",
    "metadata_created": "2015-07-27 14:53:56.740404",
    "modified_date": "",
    "capacity": "public",
    "author": null,
    "author_email": null,
    "type_of_dataset": [],
    "state": null,
    "version": "v1.00",
    "creator_user_id": null,
    "status": "http://data.europa.eu/euodp/kos/dataset-status/Completed",
    "num_resources": 18,
    "description": "Eurobarometer public opinion surveys (\u201cstandard Eurobarometer surveys\u2018) have been conducted on behalf of the Directorate-General for Information, Communication, Culture, Audiovisual of the European Commission each Spring and Autumn since Autumn 1973.  Fieldwork: March-May 2002.\n#####The results by volumes are distributed as follows:\n* Volume A: Countries\n* Volume AA: Groups of countries\n* Volume A' (AP): Trends\n* Volume AA' (AAP): Trends of groups of countries\n* Volume B: EU/socio-demographics\n* Volume B' (BP) : Trends of EU/ socio-demographics \n* Volume C: Country/socio-demographics\n  ----\nResearchers may also contact GESIS - Leibniz Institute for the Social Sciences: [https://www.gesis.org/eurobarometer](https://www.gesis.org/eurobarometer)",
    "title": "Standard Eurobarometer 57",
    "temporal_coverage_from": "",
    "tracking_summary": "560",
    "groups": [
        {
            "title": "http://publications.europa.eu/resource/authority/data-theme/GOVE"
        }
    ],
    "relationships_as_subject": [],
    "language": [
        "http://publications.europa.eu/resource/authority/language/ENG"
    ],
    "alternative_title": "Standard Eurobarometer 57",
    "url": "http://ec.europa.eu/public_opinion/archives/eb/eb57/eb57_en.htm",
    "release_date": "2014-12-10",
    "license_title": null,
    "rdf": null,
    "license_url": "http://data.europa.eu/euodp/kos/licence/EuropeanCommission",
    "organization": {
        "name": "commu",
        "title": "Directorate-General for Communication"
    }
}